{

  "data": [
  
  {
  "name":"12",
  "id":"1610520269233388",
  "lat":"48.8557014",
  "lng":"2.34007",
  "address":"12 rue dauphine  75006 Paris",
  "pins": ["lebonbon","rock","terrasse"],
  "picture":"https://fbcdn-profile-a.akamaihd.net/hprofile-ak-xat1/v/t1.0-1/p50x50/11401167_1610524379232977_5166502209900514351_n.png?oh=ec8d5bf287ad95be97970345e92d9df3&oe=567A87BC&__gda__=1449131152_157d54a4e06e132291a6cc7d12be79a4"
},
 {
  "name":"153",
  "id":"504231379719861",
  "lat":"48.8619614",
  "lng":"2.3517101",
  "address":"153 rue Saint-Martin 75003 Paris",
  "pins": ["rock","lebonbon","terrasse"],
  "picture":"https://scontent.xx.fbcdn.net/hprofile-xfa1/v/t1.0-1/p50x50/11831641_588240511318947_3434447842654720715_n.png?oh=ed0e19f6150e7a55e19e2325104f20c8&oe=565E0E16"
},
 {
  "name":"114 Up On Roof",
  "id":"484740991609685",
  "lat":"48.840229",
  "lng":"2.2354801",
  "address":"Hotel Marriott - 114 route de la Reine 92100 Boulogne-Billancourt",
  "pins": ["timeout","rock","terrasse"],
  "picture":"https://fbcdn-profile-a.akamaihd.net/static-ak/rsrc.php/v2/yW/r/U2hFrus9i5v.png"
},
 {
  "name":"116 Pages",
  "id":"1567669323514897",
  "lat":"48.8709602",
  "lng":"2.29634",
  "address":"2 rue auguste vacquerie 75116 Paris",
  "pins": ["rock","lebonbon","terrasse"],
  "picture":"https://fbcdn-profile-a.akamaihd.net/hprofile-ak-xft1/v/t1.0-1/p50x50/10994217_1568529360095560_2591488481988879258_n.jpg?oh=54200afb7f3a3b7a9e3f4de2e7b17a39&oe=56664FEC&__gda__=1450834587_9eb5c2a2bba76607d281b3703de0ca0f"
},
 {
  "name":"2 bis Café",
  "id":"261800543943016",
  "lat":"48.8476601",
  "lng":"2.3524599",
  "address":"2 bis, rue des écoles 75005 Paris",
  "pins": ["terrasse","rock","timeout"],
  "picture":"https://fbcdn-profile-a.akamaihd.net/hprofile-ak-xpa1/v/t1.0-1/c32.32.395.395/s50x50/226722_394962710626798_285452036_n.jpg?oh=7656ff29f616663dbbf91b35fc1d9563&oe=5670C5EF&__gda__=1449806317_98ec4d561956191b1312402064eaf6e3"
},
 {
  "name":"45 Tours",
  "id":"547324945310592",
  "lat":"48.850481955",
  "lng":"2.38816734773",
  "address":"45 rue de Montreuil 75011 Paris",
  "pins": ["timeout","lebonbon","rock"],
  "picture":"https://fbcdn-profile-a.akamaihd.net/hprofile-ak-xfa1/v/t1.0-1/p50x50/10392501_855263027850114_1490753807259188403_n.jpg?oh=f9ed53b1ba16c862c086e1fa5005f1f6&oe=5663B7A7&__gda__=1451057655_474ea7e562f3af3e7a9d5335f65ca885"
},
 {
  "name":"A la Marguerite",
  "id":"1615718118666330",
  "lat":"48.8854713",
  "lng":"2.3115301",
  "address":"106 rue Cardinet 75017 Paris",
  "pins": ["terrasse","rock","lebonbon"],
  "picture":"https://scontent.xx.fbcdn.net/hprofile-xtp1/v/t1.0-1/c0.0.50.50/p50x50/11947660_1621335811437894_2621867584729151942_n.jpg?oh=fd6c860825ecedf769621bace9fab80c&oe=566AD3C2"
},
 {
  "name":"Acte 3",
  "id":"164626546905131",
  "lat":"48.8561211",
  "lng":"2.3246801",
  "address":"7 rue Paul Louis Courier 75007 Paris",
  "pins": ["rock","timeout","bieres"],
  "picture":"https://fbcdn-profile-a.akamaihd.net/hprofile-ak-xta1/v/t1.0-1/c10.0.50.50/p50x50/11949157_1021099394591171_1741035003124368368_n.jpg?oh=477b2a72b6edb8fb0cf134371b69903e&oe=5664C28F&__gda__=1450456507_b9fc20b7a86fc00a9fa1aa5ed7f287fa"
},
 {
  "name":"Agence",
  "id":"209774505717848",
  "lat":"48.8875618",
  "lng":"2.3596301",
  "address":"43 rue Marx Dormoy 75018 Paris",
  "pins": ["rock","timeout","terrasse"],
  "picture":"https://fbcdn-profile-a.akamaihd.net/hprofile-ak-ash2/v/t1.0-1/c140.44.549.549/s50x50/1016516_632352766793351_1459963748_n.png?oh=5836757b62aef9f4c0beb252efe896b8&oe=5673F260&__gda__=1450447897_714cd76386f430a888359a5d710eb7ce"
},
 {
  "name":"Alcazar Club",
  "id":"360538417358086",
  "lat":"48.8545309966",
  "lng":"2.33769921989",
  "address":"62 rue mazarine 75006 Paris",
  "pins": ["bieres","rock","terrasse"],
  "picture":"https://scontent.xx.fbcdn.net/hprofile-xaf1/v/t1.0-1/p50x50/1623687_593371820741410_97334266_n.jpg?oh=c5e0c7397098a1d2c849f2398c53b320&oe=5676E9E2"
},
 {
  "name":"Alchimiste",
  "id":"120500648003666",
  "lat":"48.8432012175",
  "lng":"2.38542813137",
  "address":"181 Rue de Charenton 75012 Paris",
  "pins": ["rock","timeout","terrasse"],
  "picture":"https://fbcdn-profile-a.akamaihd.net/hprofile-ak-xat1/v/t1.0-1/p50x50/10492151_10206335576174916_5561705409647415213_n.jpg?oh=8fd606bf8298b846e6d6a820d70c136f&oe=567C1904&__gda__=1454041891_7206055719de09b125bf562d87d416a2"
},
 {
  "name":"Alimentation Générale",
  "id":"113436052054397",
  "lat":"48.8668404",
  "lng":"2.3743999",
  "address":"64 rue Jean-Pierre Timbaud 75011 Paris",
  "pins": ["rock","lebonbon","terrasse"],
  "picture":"https://fbcdn-profile-a.akamaihd.net/hprofile-ak-xpf1/v/t1.0-1/c39.39.484.484/s50x50/381295_249040385160629_799223101_n.jpg?oh=4ab81009e415ac8e15c04678e2f99cd4&oe=5670C984&__gda__=1449066472_4f820d86c3420f1b21689f45d3091108"
},
 {
  "name":"Andy Wahloo",
  "id":"158090534219775",
  "lat":"48.8645096",
  "lng":"2.3542299",
  "address":"69 rue des gravilliers 75003 Paris",
  "pins": ["timeout","lebonbon","rock"],
  "picture":"https://fbcdn-profile-a.akamaihd.net/hprofile-ak-xpf1/t5.0-1/592269_158090534219775_726167384_q.jpg"
},
 {
  "name":"Animals",
  "id":"1016334425050526",
  "lat":"48.8254318",
  "lng":"2.3276801",
  "address":"45 rue Sarrette 75014 Paris",
  "pins": ["rock","terrasse","timeout"],
  "picture":"https://scontent.xx.fbcdn.net/hprofile-xtp1/v/t1.0-1/p50x50/11207294_1190556424294991_8940481602053620451_n.jpg?oh=30af8305b580145d15539915a5e2a25d&oe=566A62E2"
},
 {
  "name":"Art Brut",
  "id":"138663742847613",
  "lat":"48.8621597",
  "lng":"2.35112",
  "address":"78, rue Quincampoix 75003 Paris",
  "pins": ["rock","lebonbon"],
  "picture":"https://fbcdn-profile-a.akamaihd.net/static-ak/rsrc.php/v2/yW/r/U2hFrus9i5v.png"
},
 {
  "name":"Atelier de Maître Albert",
  "id":"338146072915879",
  "lat":"48.8510895",
  "lng":"2.3501699",
  "address":"1, rue Maître Albert 75005 Paris",
  "pins": ["timeout","rock"],
  "picture":"https://fbcdn-profile-a.akamaihd.net/hprofile-ak-xap1/v/t1.0-1/p50x50/1477804_10152095025724311_1202354830_n.jpg?oh=d821c77d2657c05c33bf3a5c728f9941&oe=56643CB8&__gda__=1449782042_e184a0254ecc05b7b13f6fcea498dc95"
},
 {
  "name":"Atelier Ramey",
  "id":"435399229882194",
  "lat":"48.8883286",
  "lng":"2.34671",
  "address":"23 rue Ramey 75018 Paris",
  "pins": ["terrasse","rock"],
  "picture":"https://fbcdn-profile-a.akamaihd.net/hprofile-ak-xap1/v/t1.0-1/c10.0.50.50/p50x50/10268606_725670127521768_91372949057159429_n.png?oh=ff3c097d7f14107b4891421f7bda5295&oe=56763C09&__gda__=1449183501_b27785bf154bfacb6239016655bf77cd"
},
 {
  "name":"Au Bleu Cerise",
  "id":"423899300996437",
  "lat":"48.8724899",
  "lng":"2.3534501",
  "address":"6 Cour des Petites Écuries 75010 Paris",
  "pins": ["rock","terrasse"],
  "picture":"https://fbcdn-profile-a.akamaihd.net/hprofile-ak-xpf1/v/t1.0-1/c113.33.414.414/s50x50/3847_423902134329487_23489003_n.jpg?oh=a99859c6d77e6b5e68029aa23dd9b62e&oe=5678D82F&__gda__=1449529920_db946a0631fccdbe94d6cd65e3038599"
},
 {
  "name":"Au Magique",
  "id":"152505951446936",
  "lat":"48.833149",
  "lng":"2.31581",
  "address":"42 Rue Gergovie 75014 Paris",
  "pins": ["rock","bieres"],
  "picture":"https://fbcdn-profile-a.akamaihd.net/static-ak/rsrc.php/v2/y5/r/j258ei8TIHu.png"
},
 {
  "name":"Au Passage",
  "id":"143826422328468",
  "lat":"48.8616221253",
  "lng":"2.36896853686",
  "address":"1 bis passage saint sébastien 75011 Paris",
  "pins": ["terrasse","rock"],
  "picture":"https://fbcdn-profile-a.akamaihd.net/hprofile-ak-xat1/v/t1.0-1/c58.76.762.762/s50x50/11536127_984834751560960_8111417950168135702_n.jpg?oh=56a55cdd868a30b69c724bbdede587e6&oe=566FC987&__gda__=1450436461_26ebf43fb90ba320fb80740b086b0422"
},
 {
  "name":"Au Petit Chavignol",
  "id":"139380722783376",
  "lat":"48.8855896",
  "lng":"2.31024",
  "address":"78, rue de Tocqueville 75017 Paris",
  "pins": ["rock","terrasse"],
  "picture":"https://fbcdn-profile-a.akamaihd.net/static-ak/rsrc.php/v2/y5/r/j258ei8TIHu.png"
},
 {
  "name":"Au Petit Fer à Cheval",
  "id":"160781567291824",
  "lat":"48.8574104",
  "lng":"2.3575599",
  "address":"30, rue vieille-du-Temple 75004 Paris",
  "pins": ["rock","timeout"],
  "picture":"https://fbcdn-profile-a.akamaihd.net/hprofile-ak-xft1/v/t1.0-1/p50x50/1513183_789036624487666_2789896111759560134_n.jpg?oh=924838d8c8e5ec365cc17d81e0d100be&oe=567A606B&__gda__=1451155639_a60d6d5f81bb573c7d2bdcd27fa106b4"
},
 {
  "name":"Auto Passion Café",
  "id":"443510745711107",
  "lat":"48.8235893",
  "lng":"2.3247399",
  "address":"197 Boulevard Brune 75014 Paris",
  "pins": ["terrasse","rock"],
  "picture":"https://fbcdn-profile-a.akamaihd.net/hprofile-ak-xfa1/v/t1.0-1/c136.29.368.368/s50x50/423206_443510845711097_1521398945_n.jpg?oh=731c988433891a2e25af23c4b62c51e1&oe=5662D47F&__gda__=1451011774_09f5267eef5911d316f669e6c8d8fbe3"
},
 {
  "name":"Autour d'un Verre",
  "id":"110892312304479",
  "lat":"48.8738899",
  "lng":"2.3452001",
  "address":"21 Rue de Trévise 75009 Paris",
  "pins": ["bieres","rock"],
  "picture":"https://fbcdn-profile-a.akamaihd.net/hprofile-ak-xap1/v/t1.0-1/c8.0.50.50/p50x50/1175057_577251648980447_2007422042_n.jpg?oh=62e950abcb2f35c86040ac205798ff65&oe=566B0AFA&__gda__=1450616891_7e5739319c140fc5132d67d101d19c41"
},
 {
  "name":"Autour de Midi... et Minuit",
  "id":"158920794171529",
  "lat":"48.8846743991",
  "lng":"2.33352751363",
  "address":"11, Rue Lepic (Montmartre) 75018 Paris",
  "pins": ["rock","bieres"],
  "picture":"https://fbcdn-profile-a.akamaihd.net/hprofile-ak-xap1/v/t1.0-1/p50x50/1545210_10153097143196515_1099895143_n.jpg?oh=05ca5cdf02c6feef515e1697051248d8&oe=566EFA7D&__gda__=1448969951_021b7d5b5e476eb892076793e3435101"
},
 {
  "name":"Aux Folies",
  "id":"215507145246301",
  "lat":"48.8724548388",
  "lng":"2.377991746",
  "address":"8 rue de Belleville 75020 Paris",
  "pins": ["lebonbon","rock"],
  "picture":"https://scontent.xx.fbcdn.net/hprofile-xap1/v/t1.0-1/p50x50/10671367_10205831137878911_3222157185166989867_n.jpg?oh=f2ccb25fc09abe0c3a3cf3a087885878&oe=56703EF5"
},
 {
  "name":"Aux Verres De Contact",
  "id":"294030150611110",
  "lat":"48.8499184",
  "lng":"2.3498199",
  "address":"52, bld Saint Germain 75005 Paris",
  "pins": ["rock","terrasse"],
  "picture":"https://fbcdn-profile-a.akamaihd.net/hprofile-ak-xpf1/v/t1.0-1/c28.28.344.344/s50x50/302133_294031523944306_829845530_n.jpg?oh=af9fe3f19d72f305ba1aaeeaffe46e5c&oe=56683AB8&__gda__=1450425812_c83a5e9e5d2902aa7de27fb20d569673"
},
 {
  "name":"Aux Vignobles du plaisir",
  "id":"216005711212",
  "lat":"48.8287029386",
  "lng":"2.31642160634",
  "address":"88 rue Didot 75014 Paris",
  "pins": ["lebonbon","rock"],
  "picture":"https://fbcdn-profile-a.akamaihd.net/hprofile-ak-xfa1/v/t1.0-1/c247.37.466.466/s50x50/401174_10150514380281213_1041440765_n.jpg?oh=9565dae5b18ccb478820ec9937c90f75&oe=5675580D&__gda__=1449235987_33f8856e0b1664b91c260c9968b3a2e7"
},
 {
  "name":"B.58",
  "id":"489454464458841",
  "lat":"48.8740997",
  "lng":"2.34272",
  "address":"58 rue Richer 75009 Paris",
  "pins": ["rock","lebonbon"],
  "picture":"https://scontent.xx.fbcdn.net/hprofile-xpa1/v/t1.0-1/c12.12.155.155/s50x50/1044790_489461847791436_493743730_n.jpg?oh=ba3e00dd448dddd217198cc5f5d9a71b&oe=56A934DC"
},
 {
  "name":"Ballroom du Beefclub",
  "id":"128418297323376",
  "lat":"48.8641017623",
  "lng":"2.34338669549",
  "address":"58, rue Jean Jacques Rousseau 75001 Paris",
  "pins": ["rock","terrasse"],
  "picture":"https://fbcdn-profile-a.akamaihd.net/hprofile-ak-xaf1/v/t1.0-1/c8.0.50.50/p50x50/10246623_292044524294085_2642801008138041728_n.jpg?oh=3c63e2a9f6b9250a68c6200f5aa7c884&oe=56692B7E&__gda__=1450515245_091f60d9d37dcac0b02dd984f7675447"
},
 {
  "name":"Bar des Varietés",
  "id":"364834870280800",
  "lat":"48.871109",
  "lng":"2.3417399",
  "address":"12, passage des Panoramas 75002 Paris",
  "pins": ["rock","bieres"],
  "picture":"https://fbcdn-profile-a.akamaihd.net/hprofile-ak-xpf1/v/t1.0-1/c12.12.155.155/s50x50/3390_364839416947012_682453903_n.jpg?oh=a69435ba0fc30fd0fb035fce9fb61191&oe=5663CC28&__gda__=1450866247_4ea0e90225d40e1698fed1de3c4f13d4"
},
 {
  "name":"Bar Rouge",
  "id":"381541885347433",
  "lat":"48.8685417",
  "lng":"2.3602901",
  "address":"46 rue rené BOULANGER 75010 Paris",
  "pins": ["terrasse","rock"],
  "picture":"https://fbcdn-profile-a.akamaihd.net/hprofile-ak-xpa1/v/t1.0-1/p50x50/11188183_432172670284354_4494693850560722608_n.jpg?oh=0ba73cebb3aef11c370f97c5850cff59&oe=56806F6D&__gda__=1451093617_a0073093528b65afaad3a3cc85c39028"
},
 {
  "name":"Baron Rouge",
  "id":"154332554601727",
  "lat":"48.8494415",
  "lng":"2.3774199",
  "address":"1 Rue Théophile Roussel 75012 Paris",
  "pins": ["rock","timeout"],
  "picture":"https://fbcdn-profile-a.akamaihd.net/hprofile-ak-xpa1/t5.0-1/203495_154332554601727_871213272_q.jpg"
},
 {
  "name":"BarOurcq",
  "id":"211341572314513",
  "lat":"48.8864708",
  "lng":"2.3771501",
  "address":"68 quai de la Loire 75019 Paris",
  "pins": ["rock","terrasse"],
  "picture":"https://fbcdn-profile-a.akamaihd.net/hprofile-ak-xtf1/v/t1.0-1/c13.0.50.50/p50x50/11251126_789926207789377_6931462189493331171_n.jpg?oh=42f2f6f3fa54d92dc0ad6ef5495c6adc&oe=565D71C1&__gda__=1449145254_3a919ac470c03bbf983b0f869c09fe52"
},
 {
  "name":"Beaucoup",
  "id":"396544347095330",
  "lat":"48.8614998",
  "lng":"2.36608",
  "address":"7 rue Froissart 75003 Paris",
  "pins": ["rock","timeout"],
  "picture":"https://fbcdn-profile-a.akamaihd.net/hprofile-ak-xtf1/v/t1.0-1/c33.33.416.416/s50x50/14870_409808312435600_928785948_n.jpg?oh=d1be5431466278ade83f25fce4a8d8e0&oe=567EFD86&__gda__=1449440499_ebc6eecad61f0bd80d6fc8eb8dc17406"
},
 {
  "name":"Belle Equipe",
  "id":"823996554326518",
  "lat":"48.8538399",
  "lng":"2.3819699",
  "address":"92 rue de Charonne 75011 Paris",
  "pins": ["rock","lebonbon"],
  "picture":"https://fbcdn-profile-a.akamaihd.net/hprofile-ak-xfp1/v/t1.0-1/p50x50/1505144_824309654295208_4464456307506187729_n.jpg?oh=6e026b2c861d317081c3a5ae08760c16&oe=56746EE0&__gda__=1450396405_5117fd51e5f65f5bc1fe832537efec7c"
},
 {
  "name":"Belmont",
  "id":"293027377465084",
  "lat":"48.8667369551",
  "lng":"2.35007462981",
  "address":"86 Rue Réaumur 75002 Paris",
  "pins": ["terrasse","rock"],
  "picture":"https://scontent.xx.fbcdn.net/hprofile-frc3/v/t1.0-1/p50x50/1002035_10151740605111901_93148540_n.jpg?oh=d46ccb8bfdc8629e4fe8b01991427ea6&oe=5680D6D0"
},
 {
  "name":"Bianca Restaurant",
  "id":"614091095345532",
  "lat":"48.8701286",
  "lng":"2.3328199",
  "address":"2 rue du Quatre Septembre 75002 Paris",
  "pins": ["rock","bieres"],
  "picture":"https://fbcdn-profile-a.akamaihd.net/hprofile-ak-xfp1/v/t1.0-1/p50x50/10417019_715764708511503_4627059329755269959_n.jpg?oh=371cb1cd279fe3ef55e45f3a6a36e680&oe=565F47B9&__gda__=1449481439_df0a72c7e10394ef3c5fd4957890bb9a"
},
 {
  "name":"Bièrissime",
  "id":"462877600466465",
  "lat":"48.8764191",
  "lng":"2.3555901",
  "address":"85 bis boulevard Magenta 75010 Paris",
  "pins": ["terrasse","rock"],
  "picture":"https://fbcdn-profile-a.akamaihd.net/hprofile-ak-xfa1/v/t1.0-1/c28.10.123.123/s50x50/420072_462884907132401_134598610_n.jpg?oh=6b12ea958441d96f0a63e2a7eae2b30c&oe=567146AC&__gda__=1449299424_fbc46220ca844ee8eab1d09d7289d148"
},
 {
  "name":"Bistrot Blériot",
  "id":"413674405442366",
  "lat":"48.8508148",
  "lng":"2.2778893",
  "address":"7 av Versailles 75016 Paris",
  "pins": ["terrasse","rock"],
  "picture":"https://fbcdn-profile-a.akamaihd.net/hprofile-ak-xft1/v/t1.0-1/c0.0.50.50/p50x50/10414636_413698418773298_4977369955822311629_n.jpg?oh=676b012a7fb551ea1d632ac4b7a6b861&oe=566FFE37&__gda__=1453966919_07bed63a1e96d3c83ce9249497bba1d5"
},
 {
  "name":"Bistrot des Fistons",
  "id":"323457427714308",
  "lat":"48.8564179015",
  "lng":"2.30552985668",
  "address":"15 rue du champs de mars 75007 Paris",
  "pins": ["rock","bieres"],
  "picture":"https://fbcdn-profile-a.akamaihd.net/hprofile-ak-xpa1/v/t1.0-1/p50x50/10300496_739920709401309_8482384318504431273_n.jpg?oh=e1ad19b6c88846c8f217fe88603e66f5&oe=566B4448&__gda__=1449550420_4d00490f366984bf955221a86a1182b8"
},
 {
  "name":"Bistrot du sommelier",
  "id":"180859272112551",
  "lat":"48.8748093",
  "lng":"2.3181801",
  "address":"97 Boulevard Haussmann 75008 Paris",
  "pins": ["lebonbon","rock"],
  "picture":"https://scontent.xx.fbcdn.net/hprofile-xtp1/v/t1.0-1/c12.0.50.50/p50x50/11205636_395485977316545_2770014986184952679_n.jpg?oh=44d1ed4b07b94b8240b58912cdabf932&oe=5662AB46"
},
 {
  "name":"Bistrotters",
  "id":"310149349092683",
  "lat":"48.832912851",
  "lng":"2.31465620981",
  "address":"9 rue Decrès 75014 Paris",
  "pins": ["lebonbon","rock"],
  "picture":"https://fbcdn-profile-a.akamaihd.net/static-ak/rsrc.php/v2/y5/r/j258ei8TIHu.png"
},
 {
  "name":"Bizz'Art",
  "id":"109177432450881",
  "lat":"48.8790703",
  "lng":"2.3664701",
  "address":"167, Quai de Valmy - Canal St Martin 75010 Paris",
  "pins": ["timeout","rock"],
  "picture":"https://fbcdn-profile-a.akamaihd.net/hprofile-ak-xaf1/v/t1.0-1/p50x50/10801869_794094490625835_2148520571014043190_n.jpg?oh=80f20d35295ac92cf6a020082789d63e&oe=567EE479&__gda__=1454068430_7bb5e8d97e9f6e5264bb85c2f731e52f"
},
 {
  "name":"Blah Blah",
  "id":"325931357488294",
  "lat":"48.8724289",
  "lng":"2.3536301",
  "address":"4 cour des petites écuries 75010 Paris",
  "pins": ["rock","timeout"],
  "picture":"https://fbcdn-profile-a.akamaihd.net/hprofile-ak-frc3/v/t1.0-1/c196.43.543.543/s50x50/602320_331232043624892_1050815643_n.jpg?oh=b9d309ad1c7cbef88efb1843061ffacb&oe=56691EC7&__gda__=1450637086_ef5d2adaa24b5e35da4df15b0cf822e9"
},
 {
  "name":"Bloodies",
  "id":"754430054572407",
  "lat":"48.8650131448",
  "lng":"2.37612537032",
  "address":"58 avenue de la République  75011 Paris",
  "pins": ["timeout","rock"],
  "picture":"https://fbcdn-profile-a.akamaihd.net/hprofile-ak-xpf1/v/t1.0-1/p50x50/1459724_766775853337827_2073036654_n.jpg?oh=082a6514badd74afa14afb18d70521e7&oe=567092F0&__gda__=1450983112_1d650d603f471f7e075b065ac901a950"
},
 {
  "name":"Boot Café",
  "id":"641514695885641",
  "lat":"48.8611717",
  "lng":"2.36534",
  "address":"19 Rue du Pont aux Choux 75003 Paris",
  "pins": ["lebonbon","rock"],
  "picture":"https://scontent.xx.fbcdn.net/hprofile-ash4/v/t1.0-1/p50x50/1781972_641535519216892_316884264_n.jpg?oh=f2da21e24b53861f5067c7c32f0ba6e8&oe=56667F64"
},
 {
  "name":"Bouteille sur la Table",
  "id":"114906795269137",
  "lat":"48.8817215",
  "lng":"2.31779",
  "address":"2, PASSAGE GEFFROY DIDELOT 75017 Paris",
  "pins": ["rock","bieres"],
  "picture":"https://fbcdn-profile-a.akamaihd.net/hprofile-ak-xap1/v/t1.0-1/c0.11.50.50/p50x50/11667521_884041208355688_3306322597310189529_n.jpg?oh=42dd7b31d7f647a7337466f3dc3e1445&oe=5663DC71&__gda__=1449905472_757f285c5daa4437352dd72904bee344"
},
 {
  "name":"Bowling",
  "id":"464975993585866",
  "lat":"48.8895431629",
  "lng":"2.38569674363",
  "address":"Place De L'eglise 75009 Paris",
  "pins": ["lebonbon","rock"],
  "picture":"https://fbcdn-profile-a.akamaihd.net/static-ak/rsrc.php/v2/y5/r/j258ei8TIHu.png"
},
 {
  "name":"Brasserie Auteuil",
  "id":"534524579974198",
  "lat":"48.8482895",
  "lng":"2.25981",
  "address":"78 rue d'auteuil 75016 Paris",
  "pins": ["timeout","rock"],
  "picture":"https://fbcdn-profile-a.akamaihd.net/hprofile-ak-xta1/v/t1.0-1/p50x50/11666293_846131215480198_4098582729562016573_n.jpg?oh=aba40d791887e842be0117ee602784d7&oe=56AA0A18&__gda__=1450886121_2b1f2ea091f8ae16451b38c6b38b3fa1"
},
 {
  "name":"Brasserie de La Goutte d’or",
  "id":"244985455571377",
  "lat":"48.8850076282",
  "lng":"2.35244570203",
  "address":"28 rue de la Goutte d'Or 75018 Paris",
  "pins": ["rock","bieres"],
  "picture":"https://fbcdn-profile-a.akamaihd.net/hprofile-ak-xap1/v/t1.0-1/c1.0.50.50/p50x50/10959377_753511101385474_4135808368249916015_n.png?oh=aba3e8c32eab366dba6525fba6665b7e&oe=56704D9B&__gda__=1449619111_7105b88a39eb2f96c4d6a52bee5f1310"
},
 {
  "name":"Bric à Brac",
  "id":"816018621838821",
  "lat":"48.866086005",
  "lng":"2.37879042",
  "address":"108 rue Oberkampf 75011 Paris",
  "pins": ["timeout","rock"],
  "picture":"https://scontent.xx.fbcdn.net/hprofile-xtp1/v/t1.0-1/c2.7.50.50/p57x57/10891423_818552794918737_1064136918373931531_n.jpg?oh=3364facee3f3a927b8736901df25508e&oe=5667677F"
},
 {
  "name":"Brittany Bar",
  "id":"328368450593815",
  "lat":"48.8767891",
  "lng":"2.3383901",
  "address":"3-5 rue saint Lazare 75009 Paris",
  "pins": ["timeout","rock"],
  "picture":"https://scontent.xx.fbcdn.net/hprofile-xap1/v/t1.0-1/c14.14.172.172/s50x50/603021_364002107030449_1305514521_n.jpg?oh=1f0edfc7eb82ce406b64c5b12c2162fd&oe=5666F37D"
},
 {
  "name":"Bronco",
  "id":"327269987417178",
  "lat":"48.8738098",
  "lng":"2.3501699",
  "address":"39, rue des Petites Ecuries 75010 Paris",
  "pins": ["rock","bieres"],
  "picture":"https://fbcdn-profile-a.akamaihd.net/hprofile-ak-xfp1/v/t1.0-1/p50x50/11903765_695041833973323_5155339511513958643_n.jpg?oh=11dadc32f529ad53312e8b424c3e098c&oe=56A9C075&__gda__=1453920019_469b80be719bda2e3d86db30dfd9183e"
},
 {
  "name":"Buisson Ardent",
  "id":"123729400982231",
  "lat":"48.8466911",
  "lng":"2.3540399",
  "address":"25 rue JUSSIEU 75005 Paris",
  "pins": ["rock","lebonbon"],
  "picture":"https://fbcdn-profile-a.akamaihd.net/hprofile-ak-xfa1/v/t1.0-1/c10.0.50.50/p50x50/36860_133641839990987_2922506_n.jpg?oh=543d3b95c62ecbe4e9dc202f90b980e2&oe=5672F5D6&__gda__=1449578596_3fe86edce31d908116203a89df8ea56b"
},
 {
  "name":"Buzz",
  "id":"308543602495451",
  "lat":"48.8672884309",
  "lng":"2.33364720506",
  "address":"27 Avenue de l'Opéra 75001 Paris",
  "pins": ["timeout","rock"],
  "picture":"https://fbcdn-profile-a.akamaihd.net/hprofile-ak-xfa1/v/t1.0-1/p50x50/422497_397243596958784_1526144424_n.jpg?oh=cef6e69f9b641998b0adb75c54131824&oe=5679B9D4&__gda__=1450366444_158901ffaa15038402aecb9690bc7f19"
},
 {
  "name":"Café A",
  "id":"146781662051121",
  "lat":"48.8754082",
  "lng":"2.3600099",
  "address":"148 rue du Faubourg Saint-Martin 75010 Paris",
  "pins": ["rock","terrasse"],
  "picture":"https://scontent.xx.fbcdn.net/hprofile-xaf1/v/t1.0-1/p50x50/407781_259987310730555_431919919_n.jpg?oh=a1aba5017875e83d7371577f1d3bb901&oe=566DB5DB"
},
 {
  "name":"Café Bonnie",
  "id":"51667883422",
  "lat":"48.8743515",
  "lng":"2.3619599",
  "address":"9 rue des Récollets 75010 Paris",
  "pins": ["bieres","rock"],
  "picture":"https://fbcdn-profile-a.akamaihd.net/hprofile-ak-frc3/v/t1.0-1/c42.42.520.520/s50x50/557867_10151497185328423_1212914927_n.jpg?oh=c45ea430d29bc8823de88a751c4c3e02&oe=56711DA7&__gda__=1449584180_c3421119a08bbe5fb46d05c1a04c5bd8"
},
 {
  "name":"Café Chérie",
  "id":"1421964738108148",
  "lat":"48.8740997",
  "lng":"2.3752401",
  "address":"44 Boulevard de la Villette 75020 Paris",
  "pins": ["timeout","rock"],
  "picture":"https://fbcdn-profile-a.akamaihd.net/hprofile-ak-xap1/v/t1.0-1/p50x50/19202_1421964804774808_7050143094071348655_n.jpg?oh=63e2adf2fd8761dd7f6ae97e5c4fa6ab&oe=5669AA9F&__gda__=1449242632_41df84a3e85e68f93438e9b3e45b6926"
},
 {
  "name":"Café Chilango",
  "id":"613919915330554",
  "lat":"48.8662179698",
  "lng":"2.36987249299",
  "address":"82 rue de la Folie Méricourt 75011 Paris",
  "pins": ["timeout","rock"],
  "picture":"https://scontent.xx.fbcdn.net/hprofile-xaf1/v/t1.0-1/c0.0.50.50/p50x50/10298692_758719007517310_8831692121689411675_n.jpg?oh=53d4cc11283de1e52f25fe04dbb81b03&oe=56677C3D"
},
 {
  "name":"Café de l'Industrie",
  "id":"330954120300440",
  "lat":"48.8554802",
  "lng":"2.3719499",
  "address":"16 rue Saint-Sabin 75011 Paris",
  "pins": ["rock","terrasse"],
  "picture":"https://fbcdn-profile-a.akamaihd.net/hprofile-ak-xft1/v/t1.0-1/p50x50/10157147_732974983414625_3406992790462796253_n.jpg?oh=d7c7ef8bdd66469ab1af1ee644dbb22f&oe=56A9F7B9&__gda__=1450774189_295c68058e9ddb7e32475f6c50a28286"
},
 {
  "name":"Café de la Presse",
  "id":"1471441216402097",
  "lat":"48.8503914",
  "lng":"2.3689101",
  "address":"36, boulevard de la Bastille 75012 Paris",
  "pins": ["rock","timeout"],
  "picture":"https://scontent.xx.fbcdn.net/hprofile-xfp1/v/t1.0-1/c10.0.50.50/p50x50/1969150_1471733549706197_280792124_n.png?oh=b6dd7bef2e8ac2234bcba50369f3b3a8&oe=5671D94A"
},
 {
  "name":"Café des Anges",
  "id":"152173031508851",
  "lat":"48.8554382",
  "lng":"2.3744199",
  "address":"66 Rue de la Roquette 75011 Paris",
  "pins": ["rock","bieres"],
  "picture":"https://fbcdn-profile-a.akamaihd.net/hprofile-ak-xaf1/v/t1.0-1/c0.0.50.50/p50x50/11079672_854736327919181_1423571805591686544_n.jpg?oh=89671f391a9720a769efd6bc18219410&oe=567FFA8A&__gda__=1449961433_78a7f58e7799f5294ab6a5c6d9f672b6"
},
 {
  "name":"Café du Commerce",
  "id":"196950773677017",
  "lat":"48.8847618",
  "lng":"2.3471",
  "address":"13 rue Clignancourt 75018 Paris",
  "pins": ["rock","terrasse"],
  "picture":"https://fbcdn-profile-a.akamaihd.net/hprofile-ak-xla1/v/t1.0-1/p50x50/11225316_958638130841607_3722057671376054239_n.jpg?oh=aee2dab6c4c9adcf0a08e3c7764b3cf2&oe=56AB7D3E&__gda__=1450049571_382039b8586b427100bedca0fc7ceca2"
},
 {
  "name":"Café du Marché",
  "id":"489211284444967",
  "lat":"48.8565637506",
  "lng":"2.3064224825",
  "address":"38, rue Cler 75007 Paris",
  "pins": ["lebonbon","rock"],
  "picture":"https://scontent.xx.fbcdn.net/hprofile-xtf1/v/t1.0-1/c21.0.50.50/p50x50/10407595_840534365979322_3164546842621353891_n.jpg?oh=c43710c13cc82d477ffe7a72b970057f&oe=5669C822"
},
 {
  "name":"Café Moderne",
  "id":"236875206441492",
  "lat":"48.8549365265",
  "lng":"2.37567281283",
  "address":"19 rue keller 75011 Paris",
  "pins": ["rock","lebonbon"],
  "picture":"https://scontent.xx.fbcdn.net/hprofile-ash2/v/t1.0-1/c9.0.50.50/p50x50/578365_236878026441210_803023156_n.jpg?oh=8dfdf7be7cb3a5477f32ff51f2f53081&oe=5667F59A"
},
 {
  "name":"Café Oz Denfert-Rochereau",
  "id":"222560654424796",
  "lat":"48.8332252984",
  "lng":"2.3337025633",
  "address":"3, place Denfert-Rochereau 75014 Paris",
  "pins": ["terrasse","rock"],
  "picture":"https://fbcdn-profile-a.akamaihd.net/hprofile-ak-xpf1/v/t1.0-1/c0.0.50.50/p50x50/1472072_747746051906251_393091084_n.jpg?oh=b6699dd7e43b111cec93dfa7969dca3a&oe=5668CEF7&__gda__=1451215196_eb40d13d07cd532ea4612b1342f49ec3"
},
 {
  "name":"Café Titon",
  "id":"145478595548113",
  "lat":"48.8528595",
  "lng":"2.3863599",
  "address":"34, rue titon 75011 Paris",
  "pins": ["rock","timeout"],
  "picture":"https://scontent.xx.fbcdn.net/hprofile-frc3/v/t1.0-1/c55.110.552.552/s50x50/602862_402138419882128_1433505368_n.jpg?oh=448166cae14ea181752a61ecc5c281e7&oe=56A9A053"
},
 {
  "name":"Café Zèd",
  "id":"140257522708919",
  "lat":"48.8401985",
  "lng":"2.35023",
  "address":"46 rue Daubenton 75005 Paris",
  "pins": ["bieres","rock"],
  "picture":"https://fbcdn-profile-a.akamaihd.net/hprofile-ak-xfa1/v/t1.0-1/c127.37.466.466/s50x50/200532_140284416039563_6210910_n.jpg?oh=0444003faad810a1114658baeef94d64&oe=566305E0&__gda__=1450421353_6ed5de6d7ab779eb7457e400855dbe4e"
},
 {
  "name":"Cantine de Belleville",
  "id":"106008176132747",
  "lat":"48.8707886",
  "lng":"2.3787501",
  "address":"108 boulevard de Belleville 75020 Paris",
  "pins": ["timeout","rock"],
  "picture":"https://fbcdn-profile-a.akamaihd.net/hprofile-ak-xpf1/v/t1.0-1/c0.0.50.50/p50x50/11902360_994672340599655_6147145614384504189_n.jpg?oh=e381f860630260ba1892947f165bba10&oe=566C3D5E&__gda__=1451043339_7ecca76a1374b6bfb72c9647dc4fe8c9"
},
 {
  "name":"Cantine Max Y Jeremy",
  "id":"477764229036086",
  "lat":"48.8729401",
  "lng":"2.3543301",
  "address":"75 rue du Faubourg Saint Denis 75010 Paris",
  "pins": ["rock","terrasse"],
  "picture":"https://scontent.xx.fbcdn.net/hprofile-xpf1/v/t1.0-1/p50x50/10303808_477767899035719_7275830402176002725_n.png?oh=5aa697286278d1ab81d1feb972ef42a1&oe=568034A7"
},
 {
  "name":"Carreau du Temple",
  "id":"471703352912611",
  "lat":"48.8646317",
  "lng":"2.3622501",
  "address":"4 rue Eugène Spuller - Accueil Billetterie 2 rue Perrée 75003 Paris",
  "pins": ["terrasse","rock"],
  "picture":"https://fbcdn-profile-a.akamaihd.net/hprofile-ak-xtf1/v/t1.0-1/c0.5.50.50/p50x50/1384184_531752246907721_105281229_n.jpg?oh=db096d233422f91cc067601f848ee3a2&oe=5664D674&__gda__=1450187570_9562ae7df1ab541c6faeb15217352777"
},
 {
  "name":"Casbah",
  "id":"308366769241379",
  "lat":"48.851534747",
  "lng":"2.38079965525",
  "address":"18-20 rue de la Forge Royale 75011 Paris",
  "pins": ["lebonbon","rock"],
  "picture":"https://fbcdn-profile-a.akamaihd.net/hprofile-ak-xap1/v/t1.0-1/p50x50/536750_318683174876405_1638833774_n.jpg?oh=d44c28187e663d43acdc9388970c0610&oe=566547F8&__gda__=1451156595_2dce506dc683404fba1ab6cc4059a8b2"
},
 {
  "name":"Caveau des Légendes",
  "id":"193049070727890",
  "lat":"48.8550987",
  "lng":"2.33529",
  "address":"22 rue Jacob 75006 Paris",
  "pins": ["terrasse","rock"],
  "picture":"https://fbcdn-profile-a.akamaihd.net/hprofile-ak-xap1/v/t1.0-1/c8.0.50.50/p50x50/1378568_918267158206074_6408633299068815004_n.jpg?oh=9eb2028807dacdd2269a3c70cee9c2c7&oe=5678BF95&__gda__=1450667409_5e1f2bb46cd688ab7b75bab631f9090e"
},
 {
  "name":"Cavern",
  "id":"293655230673367",
  "lat":"48.8551788",
  "lng":"2.3398299",
  "address":"21 rue Dauphine 75006 Paris",
  "pins": ["terrasse","rock"],
  "picture":"https://scontent.xx.fbcdn.net/hprofile-xpa1/v/t1.0-1/c10.0.50.50/p50x50/10703777_799240286781523_4867689140025342421_n.png?oh=61ef00766bbe5769f289228c46b576a4&oe=567AF3C3"
},
 {
  "name":"Caves de Reuilly",
  "id":"406621429413089",
  "lat":"48.8392982",
  "lng":"2.3907399",
  "address":"11 boulevard de Reuilly 75012 Paris",
  "pins": ["bieres","rock"],
  "picture":"https://scontent.xx.fbcdn.net/hprofile-xap1/v/t1.0-1/c51.0.50.50/p50x50/1535762_585363008205596_1163780241_n.png?oh=7e828e7c0ecdd5fe678bb63d36fe9040&oe=566FFD29"
},
 {
  "name":"Caves Legrand Filles & Fils",
  "id":"156242721064593",
  "lat":"48.8662701221",
  "lng":"2.33962193481",
  "address":"1, rue de la Banque 75002 Paris",
  "pins": ["rock","bieres"],
  "picture":"https://fbcdn-profile-a.akamaihd.net/hprofile-ak-xfa1/v/t1.0-1/c32.79.538.538/s50x50/404917_528030240552504_85668132_n.jpg?oh=6458864852f790ee80d2ac2a8fb2fa9a&oe=56A917FD&__gda__=1454095220_d7fc57f0b0e9427fa7f57a9ccac519b2"
},
 {
  "name":"Cercle",
  "id":"308981362571552",
  "lat":"48.876448614",
  "lng":"2.32798282744",
  "address":"94 Rue Saint-Lazare 75009 Paris",
  "pins": ["rock","timeout"],
  "picture":"https://fbcdn-profile-a.akamaihd.net/hprofile-ak-xfp1/v/t1.0-1/c0.12.50.50/p50x50/11880528_662135603922791_5750684943392618535_n.jpg?oh=16e732017c77cddd9737924008ee9c99&oe=56AAE3BD&__gda__=1449070996_e1c64ef391a271afdf146cec9b41421c"
},
 {
  "name":"Certa",
  "id":"609658335766627",
  "lat":"48.8747482",
  "lng":"2.3259101",
  "address":"5 rue de L'Isly 75008 Paris",
  "pins": ["lebonbon","rock"],
  "picture":"https://fbcdn-profile-a.akamaihd.net/hprofile-ak-xta1/v/t1.0-1/c8.0.50.50/p50x50/10665800_746457172086742_3801025732629660149_n.jpg?oh=6b77f0a5e29d531fac93d155b591e349&oe=56A93B07&__gda__=1450060212_51d009aa3c1b46d5ade01566c4a59d3a"
},
 {
  "name":"Charlie Birdy - Commerce",
  "id":"140982152764034",
  "lat":"48.8433113",
  "lng":"2.2934401",
  "address":"Charlie Birdy 1 place Etienne Pernet, 75015 Paris M° Commerce 01 48 28 06 06 75015 Paris",
  "pins": ["rock","terrasse"],
  "picture":"https://fbcdn-profile-a.akamaihd.net/hprofile-ak-xfa1/v/t1.0-1/p50x50/1043973_147751898753726_1223431958_n.jpg?oh=2ef7fa5cb22d0da3dc3e7032547c01d1&oe=566F7C39&__gda__=1450870605_1d460a5db7cd134c68ba4546103fe3a5"
},
 {
  "name":"Château d'Eau",
  "id":"111973818863166",
  "lat":"48.8727777778",
  "lng":"2.35611111111",
  "address":"Boulevard de Strasbourg 75010 Paris",
  "pins": ["terrasse","rock"],
  "picture":"https://fbexternal-a.akamaihd.net/safe_image.php?d=AQDdfMHjqqefmI55&w=50&h=50&url=https%3A%2F%2Fupload.wikimedia.org%2Fwikipedia%2Fcommons%2Fthumb%2F5%2F53%2FMetro_a_Paris_01.JPG%2F720px-Metro_a_Paris_01.JPG&crop&fallback=hub_likes&prefix=q"
},
 {
  "name":"Chez Bouboule",
  "id":"777381835648552",
  "lat":"48.8819224236",
  "lng":"2.346633998",
  "address":"0 AVENUE TRUDAINE 75009 Paris",
  "pins": ["terrasse","rock"],
  "picture":"https://scontent.xx.fbcdn.net/hprofile-xfa1/v/t1.0-1/c1.0.50.50/p50x50/10930081_802227076497361_5841134458502235436_n.png?oh=990d302a3ea3c13641620d104475fce4&oe=5675DCE8"
},
 {
  "name":"Chez Carmen",
  "id":"687560224624312",
  "lat":"48.8712514484",
  "lng":"2.34154247416",
  "address":"Rue vivienne  75002 Paris",
  "pins": ["lebonbon","rock"],
  "picture":"https://fbcdn-profile-a.akamaihd.net/static-ak/rsrc.php/v2/y5/r/j258ei8TIHu.png"
},
 {
  "name":"Chez Georges",
  "id":"173301037327",
  "lat":"48.8521881",
  "lng":"2.33374",
  "address":"11 rue des Canettes 75006 Paris",
  "pins": ["lebonbon","rock"],
  "picture":"https://scontent.xx.fbcdn.net/hprofile-xpa1/v/t1.0-1/p50x50/11707361_10153459403632328_5221049375636567656_n.jpg?oh=7955560fb2ea5a74b1bb3af1a659e3c5&oe=5670D28C"
},
 {
  "name":"Chez Justine",
  "id":"1656294281271884",
  "lat":"48.8667023095",
  "lng":"2.37779823045",
  "address":"96 rue Oberkampf 75011 Paris",
  "pins": ["terrasse","rock"],
  "picture":"https://fbcdn-profile-a.akamaihd.net/hprofile-ak-xfa1/v/t1.0-1/p50x50/11037477_1656692431232069_8619684565184711375_n.jpg?oh=25a091bc8ebfa7b0856833e241e6fc8b&oe=566FA9CD&__gda__=1450961227_3c1c8780668176867d6318619728dc3a"
},
 {
  "name":"Chez Marie",
  "id":"378237585672575",
  "lat":"48.8732432317",
  "lng":"2.370719545",
  "address":"219 Rue Saint Maur 75010 Paris",
  "pins": ["rock","timeout"],
  "picture":"https://fbcdn-profile-a.akamaihd.net/hprofile-ak-xfa1/v/t1.0-1/c2.0.50.50/p50x50/1901366_378240195672314_3715225560447263304_n.png?oh=8312ec78dc007838c5480eebb6531997&oe=565DDD63&__gda__=1449889227_0416383170fb1ae36b6f6fd6f53932ef"
},
 {
  "name":"Chez Nous",
  "id":"650222361680339",
  "lat":"48.855751",
  "lng":"2.3401101",
  "address":"10 Rue Dauphine 75006 Paris",
  "pins": ["rock","lebonbon"],
  "picture":"https://scontent.xx.fbcdn.net/hprofile-xpa1/v/t1.0-1/p50x50/1374075_650227015013207_1309443420_n.jpg?oh=274ec71f10a18b9dfbc3e6ca83a90d88&oe=567DF1F0"
},
 {
  "name":"Chez Petit Jerry",
  "id":"845129855543976",
  "lat":"48.8726506836",
  "lng":"2.37562179565",
  "address":"4 rue civiale  75010 Paris",
  "pins": ["bieres","rock"],
  "picture":"https://fbcdn-profile-a.akamaihd.net/hprofile-ak-xaf1/v/t1.0-1/c8.0.50.50/p50x50/10302045_845138952209733_1116794913424889215_n.jpg?oh=e6d694e12d94009852d4a0f5d8adf192&oe=567D1FC8&__gda__=1449741467_4715cd2ae95fc99a5639e5cc35410d97"
},
 {
  "name":"Cicciolina",
  "id":"276691699202492",
  "lat":"48.8657064471",
  "lng":"2.38199945526",
  "address":"11 rue Crespin Dugast 75011 Paris",
  "pins": ["rock","terrasse"],
  "picture":"https://fbcdn-profile-a.akamaihd.net/hprofile-ak-xfa1/v/t1.0-1/p50x50/1487317_309118132626515_4431436234476267619_n.jpg?oh=cbdad6f0fecd29951847d15330fb6b5c&oe=5674625E&__gda__=1450006796_161fbf901c307e06e7873f6a8045a5ab"
},
 {
  "name":"Cinquante",
  "id":"195059667184887",
  "lat":"48.8719482",
  "lng":"2.3626699",
  "address":"50, rue de Lancry 75010 Paris",
  "pins": ["rock","lebonbon"],
  "picture":"https://fbcdn-profile-a.akamaihd.net/hprofile-ak-xpa1/v/t1.0-1/p50x50/11822379_1009161172441395_6072296448573436954_n.jpg?oh=b4d3463dbafd009216c8b09cb494e2f3&oe=56673E14&__gda__=1449118507_208b88fd52a3210eb7783bfdfd8ef829"
},
 {
  "name":"Clichy's Tavern",
  "id":"177909869022569",
  "lat":"48.8845058936",
  "lng":"2.32940184861",
  "address":"Boulevard De Clichy 75018 Paris",
  "pins": ["timeout","rock"],
  "picture":"https://fbcdn-profile-a.akamaihd.net/hprofile-ak-xfp1/v/t1.0-1/p50x50/1521727_10153745581680354_786885440_n.jpg?oh=070438060689cbe6d71ddd7d128bac2d&oe=565D33EA&__gda__=1450538433_f928b5c1e96e95608dc704e7bf25ad10"
},
 {
  "name":"Clichy’s Tavern",
  "id":"177909869022569",
  "lat":"48.8845058936",
  "lng":"2.32940184861",
  "address":"Boulevard De Clichy 75018 Paris",
  "pins": ["rock","timeout"],
  "picture":"https://fbcdn-profile-a.akamaihd.net/hprofile-ak-xfp1/v/t1.0-1/p50x50/1521727_10153745581680354_786885440_n.jpg?oh=070438060689cbe6d71ddd7d128bac2d&oe=565D33EA&__gda__=1450538433_f928b5c1e96e95608dc704e7bf25ad10"
},
 {
  "name":"Clown Bar",
  "id":"647115225346894",
  "lat":"48.8636179",
  "lng":"2.367141",
  "address":"114 rue Amelot 75011 Paris",
  "pins": ["rock","terrasse"],
  "picture":"https://fbexternal-a.akamaihd.net/safe_image.php?d=AQDdIHKJ6KqvcZgm&w=50&h=50&url=https%3A%2F%2Fupload.wikimedia.org%2Fwikipedia%2Fcommons%2Fthumb%2F6%2F64%2FLe_Clown-Bar_%2528int%25C3%25A9rieur%2529.jpg%2F720px-Le_Clown-Bar_%2528int%25C3%25A9rieur%2529.jpg&crop&fallback=hub_likes&prefix=q"
},
 {
  "name":"Club des Saints Pères",
  "id":"425920720804138",
  "lat":"48.8569717",
  "lng":"2.3321199",
  "address":"10 rue des Saint-Pères 75007 Paris",
  "pins": ["rock","lebonbon"],
  "picture":"https://scontent.xx.fbcdn.net/hprofile-xpt1/v/t1.0-1/c51.28.347.347/s50x50/18028_449305505132326_1179576027_n.jpg?oh=df9ec345fd673fda7e2979cbcb84c1ee&oe=5673EE17"
},
 {
  "name":"Coeur Fou",
  "id":"332939823428098",
  "lat":"48.8659706",
  "lng":"2.34448",
  "address":"55 Rue Montmartre 75002 Paris",
  "pins": ["rock","terrasse"],
  "picture":"https://scontent.xx.fbcdn.net/hprofile-xfa1/v/t1.0-1/p50x50/10486057_691738037548273_792314666734825839_n.jpg?oh=d55c9828a58e04ada2a364bc482f1f14&oe=56718949"
},
 {
  "name":"Coltrane",
  "id":"1610688662512105",
  "lat":"48.8674507",
  "lng":"2.3587301",
  "address":"38 rue Notre Dame de Nazareth 75003 Paris",
  "pins": ["lebonbon","rock"],
  "picture":"https://fbcdn-profile-a.akamaihd.net/hprofile-ak-xlt1/v/t1.0-1/p50x50/1932238_1613299648917673_4799542231751516891_n.jpg?oh=be45bf92882dc65b0843c6ba6472d47f&oe=56740F5E&__gda__=1450916103_860d6b66f1ac2897cbd6381d3e07bcd7"
},
 {
  "name":"Comedy Club",
  "id":"219081991489125",
  "lat":"48.8706774813",
  "lng":"2.34845143883",
  "address":"42 Boulevard Bonne Nouvelle  75010 Paris",
  "pins": ["terrasse","rock"],
  "picture":"https://fbcdn-profile-a.akamaihd.net/hprofile-ak-xtf1/v/t1.0-1/p50x50/11403067_942169512513699_3104150188384868332_n.png?oh=179032ae1f4cf333572e0be0e02f96e5&oe=567F789E&__gda__=1450179800_9b5a0d34b22c434ed29085af4fa0bb29"
},
 {
  "name":"Compas",
  "id":"810823185663809",
  "lat":"48.8651886",
  "lng":"2.3470299",
  "address":"62, rue Montorgueil 75002 Paris",
  "pins": ["lebonbon","rock"],
  "picture":"https://fbcdn-profile-a.akamaihd.net/hprofile-ak-xft1/v/t1.0-1/c4.0.50.50/p50x50/10409140_813888535357274_7165966897676958617_n.png?oh=a6eeac19b04cc675ed7c52234353ff55&oe=567A9567&__gda__=1450745111_f177bbf3d0f395273784dc1a2bd27941"
},
 {
  "name":"Connolly’s corner",
  "id":"197229523633334",
  "lat":"48.8410683",
  "lng":"2.3509099",
  "address":"12 rue de Mirbel 75005 Paris",
  "pins": ["rock","timeout"],
  "picture":"https://scontent.xx.fbcdn.net/hprofile-xfp1/v/t1.0-1/p50x50/11070417_10153942049754881_715548789553791820_n.jpg?oh=689a8c22bd09293be76af5b260e6ccab&oe=567AE692"
},
 {
  "name":"CopperBay",
  "id":"804876182871023",
  "lat":"48.8698502",
  "lng":"2.35711",
  "address":"5 Rue Bouchardon 75010 Paris",
  "pins": ["rock","timeout"],
  "picture":"https://fbcdn-profile-a.akamaihd.net/hprofile-ak-xpf1/v/t1.0-1/p50x50/10399989_830386650319976_3111245830984020691_n.jpg?oh=055966e6cd6ec39de859b558df0a3061&oe=567CB9F6&__gda__=1450161501_df344460d354a05ef065de06821f27ad"
},
 {
  "name":"Coquette",
  "id":"1477016355846409",
  "lat":"48.8718869646",
  "lng":"2.33351639882",
  "address":"4 rue Mayerbeer 75009 Paris",
  "pins": ["timeout","rock"],
  "picture":"https://fbcdn-profile-a.akamaihd.net/static-ak/rsrc.php/v2/yW/r/U2hFrus9i5v.png"
},
 {
  "name":"Corcoran’s Bastille",
  "id":"373624469336143",
  "lat":"48.8521881",
  "lng":"2.37304",
  "address":"53 rue du Faubourg St Antoine 75011 Paris",
  "pins": ["rock","lebonbon"],
  "picture":"https://scontent.xx.fbcdn.net/hprofile-xfa1/v/t1.0-1/c66.66.828.828/s50x50/483426_538916986140223_766487584_n.jpg?oh=8789bb0fa0d4ff3ec89151bc4b189afd&oe=565DD5C1"
},
 {
  "name":"Cotte Rôti",
  "id":"202253119840516",
  "lat":"48.8481903",
  "lng":"2.3766999",
  "address":"1 rue de Cotte PARIS Paris",
  "pins": ["terrasse","rock"],
  "picture":"https://fbcdn-profile-a.akamaihd.net/hprofile-ak-xap1/v/t1.0-1/p50x50/1001906_10202619262575122_900704286_n.jpg?oh=e2330d18718530e4f6df8b9cb883d9fe&oe=566975C5&__gda__=1450727442_fc4e2b3ea72a800a789cf6b2cd55346e"
},
 {
  "name":"Cubana Café",
  "id":"241302529325491",
  "lat":"48.842701",
  "lng":"2.3288901",
  "address":"45, 47 rue Vavin 75006 Paris",
  "pins": ["rock","terrasse"],
  "picture":"https://fbcdn-profile-a.akamaihd.net/hprofile-ak-xpf1/v/t1.0-1/p50x50/10509480_540992639356477_4437110204719806061_n.jpg?oh=8a9250c0cb73fd7c9faf4af530016667&oe=567E77FD&__gda__=1449680982_c1931916008ffdbee2252e95cb280303"
},
 {
  "name":"Dancing de la Coupole",
  "id":"241424642731631",
  "lat":"48.8423004",
  "lng":"2.3280499",
  "address":"102 boulevard du Montparnasse 75014 Paris",
  "pins": ["timeout","rock"],
  "picture":"https://fbcdn-profile-a.akamaihd.net/static-ak/rsrc.php/v2/y5/r/j258ei8TIHu.png"
},
 {
  "name":"Danny Hills",
  "id":"523573521018064",
  "lat":"48.8789783882",
  "lng":"2.37819759221",
  "address":"84 avenue Secrétan  75019  Paris",
  "pins": ["terrasse","rock"],
  "picture":"https://scontent.xx.fbcdn.net/hprofile-xap1/v/t1.0-1/c1.0.50.50/p50x50/10352740_725189164189831_7387838096612525089_n.jpg?oh=103b0ce7c9f8e4ffdea52b559f0c35b1&oe=566BE799"
},
 {
  "name":"Dans Le Noir ?",
  "id":"131467220232982",
  "lat":"48.8613281",
  "lng":"2.3505499",
  "address":"51, Rue Quincampoix  75004 Paris",
  "pins": ["lebonbon","rock"],
  "picture":"https://fbcdn-profile-a.akamaihd.net/hprofile-ak-xfa1/v/t1.0-1/p50x50/542360_420487434664291_549102205_n.jpg?oh=852bde2a49e0c4caf0a378f7104b88f9&oe=567018F4&__gda__=1449452317_43e517775957146ce868635d8469f1d1"
},
 {
  "name":"Defender",
  "id":"261672242193",
  "lat":"48.8633819483",
  "lng":"2.33581832645",
  "address":"Place André Malraux 75001 Paris",
  "pins": ["rock","timeout"],
  "picture":"https://scontent.xx.fbcdn.net/hprofile-xfa1/v/t1.0-1/c153.33.414.414/s50x50/63622_470817992193_2400333_n.jpg?oh=b512fd1fe529ae52f12bb381eda0ef7a&oe=5679B188"
},
 {
  "name":"Deux Plus Deux",
  "id":"780309075369882",
  "lat":"48.8615584261",
  "lng":"2.37063957167",
  "address":"33 Rue Saint-Sébastien 75011 Paris",
  "pins": ["bieres","rock"],
  "picture":"https://fbcdn-profile-a.akamaihd.net/hprofile-ak-prn2/v/t1.0-1/p50x50/10361500_823758097691646_2900508743872024618_n.jpg?oh=4dd5d9d782b667ee93c73718fdc6dfb3&oe=56665F04&__gda__=1449618879_66e5fc8232e3cb4aad91bff196d53362"
},
 {
  "name":"Divette de Montmartre",
  "id":"162370170451837",
  "lat":"48.8912888",
  "lng":"2.3393199",
  "address":"136 rue marcadet 75018 Paris",
  "pins": ["rock","terrasse"],
  "picture":"https://scontent.xx.fbcdn.net/hprofile-frc3/v/t1.0-1/c9.0.50.50/p50x50/1010921_10151841715204566_1880147517_n.jpg?oh=7b82e22bf6a69f76262ce295c9c6dc1f&oe=566C68A4"
},
 {
  "name":"Dix Bar",
  "id":"117058621661861",
  "lat":"48.8673897",
  "lng":"2.3652401",
  "address":"10 Place de la République 75011 Paris",
  "pins": ["rock","bieres"],
  "picture":"https://fbcdn-profile-a.akamaihd.net/hprofile-ak-xfa1/v/t1.0-1/c69.66.822.822/s50x50/1240093_640815495952835_815735264_n.png?oh=4b5794b8c8785d1c727ad4918c5937ac&oe=56778BC9&__gda__=1451010297_67c0cb59b8329b09534217deb9c302c7"
},
 {
  "name":"Dôme du Marais",
  "id":"197297457002435",
  "lat":"48.8590813",
  "lng":"2.35814",
  "address":"53 bis rue des Francs Bourgeois 75004 Paris",
  "pins": ["timeout","rock"],
  "picture":"https://fbcdn-profile-a.akamaihd.net/hprofile-ak-prn2/v/t1.0-1/c33.33.414.414/s50x50/933934_528896220509222_1280771552_n.png?oh=5792c9cb9d975decaecc9f0f69e0bdd0&oe=567C4D53&__gda__=1450845113_44aa4b69ee98c05efb449ca420b24832"
},
 {
  "name":"Düo",
  "id":"520718984648268",
  "lat":"48.8645130594",
  "lng":"2.37339049194",
  "address":"24 rue du marché Popincourt 75011 Paris",
  "pins": ["timeout","rock"],
  "picture":"https://scontent.xx.fbcdn.net/hprofile-xpa1/v/t1.0-1/c0.0.50.50/p50x50/11149383_860606080659555_4958709577481103091_n.jpg?oh=a0c8dbfdcfed82f53ad3f0bb8a2c21fb&oe=565D3CBC"
},
 {
  "name":"Durand Dupont",
  "id":"247159712008533",
  "lat":"48.8807487",
  "lng":"2.2755899",
  "address":"14 Place du marché 92200 Neuilly-sur-Seine",
  "pins": ["terrasse","rock"],
  "picture":"https://fbcdn-profile-a.akamaihd.net/hprofile-ak-xfa1/v/t1.0-1/c171.37.459.459/s50x50/424436_319406031450567_216155503_n.jpg?oh=42435f64bf3ef281d36df95e4803cd2e&oe=56650BDE&__gda__=1449688046_6c8e86afdb12bce24be26e03bc71bd4b"
},
 {
  "name":"Echelle de Jacob",
  "id":"125211930867353",
  "lat":"48.8549004",
  "lng":"2.33586",
  "address":"12 rue Jacob 75006 Paris",
  "pins": ["lebonbon","rock"],
  "picture":"https://fbcdn-profile-a.akamaihd.net/hprofile-ak-xfp1/v/t1.0-1/c28.28.344.344/s50x50/72040_125211984200681_5587729_n.jpg?oh=6b941a7627a724d9f723415b0857370a&oe=56A982D1&__gda__=1453896375_cbaac726a162574521060eadfcd4ca2d"
},
 {
  "name":"El Tast",
  "id":"1522181698068086",
  "lat":"48.8937093628",
  "lng":"2.3431861071",
  "address":"70 Rue Duhesme 75018 Paris",
  "pins": ["rock","lebonbon"],
  "picture":"https://scontent.xx.fbcdn.net/hprofile-xfp1/v/t1.0-1/p50x50/10438469_1522671138019142_1023294799735743818_n.jpg?oh=84ae865cb8282f56728dcd5e2f23cce0&oe=56AADB93"
},
 {
  "name":"El Urbano",
  "id":"234453226762216",
  "lat":"48.8663406",
  "lng":"2.3815899",
  "address":"3 Rue Crespin Du gast 75011 Paris",
  "pins": ["lebonbon","rock"],
  "picture":"https://fbcdn-profile-a.akamaihd.net/hprofile-ak-ash4/v/t1.0-1/c0.11.50.50/p50x50/10245522_235861623288043_936666440274950963_n.jpg?oh=35137b3f2dd8d55f85981fd50f367a9f&oe=5671AC10&__gda__=1454070497_3d3666c4c8ec2c43bd029193aee7f2f3"
},
 {
  "name":"En attendant Rosa",
  "id":"621791967910466",
  "lat":"48.8631744563",
  "lng":"2.31530036378",
  "address":"37 quai d'Orsay, entre les ponts Concorde et Alexandre III 7e Paris 75008 Paris",
  "pins": ["lebonbon","rock"],
  "picture":"https://fbcdn-profile-a.akamaihd.net/static-ak/rsrc.php/v2/yW/r/U2hFrus9i5v.png"
},
 {
  "name":"Epicerie Musicale",
  "id":"152444731500263",
  "lat":"48.8704796",
  "lng":"2.36551",
  "address":"55 bis Quai de Valmy 75010 Paris",
  "pins": ["rock","timeout"],
  "picture":"https://scontent.xx.fbcdn.net/hprofile-xpf1/v/t1.0-1/c0.0.50.50/p50x50/10926436_1107286862682707_5690489066290434383_n.png?oh=d3635d2cfb9b485709096542276c2eb5&oe=5672FB35"
},
 {
  "name":"Epicurianu",
  "id":"421926544652281",
  "lat":"48.8677406",
  "lng":"2.36888",
  "address":"104 rue de la Folie-Méricourt 75011 Paris",
  "pins": ["rock","bieres"],
  "picture":"https://fbcdn-profile-a.akamaihd.net/hprofile-ak-xpa1/v/t1.0-1/p50x50/10253866_424962184348717_6717690409424709939_n.jpg?oh=abd9860087446ab6bbc8f5cbc947685a&oe=56716164&__gda__=1451030136_808ca574b95ed8b734637ead9dec100f"
},
 {
  "name":"Epure",
  "id":"151955681679952",
  "lat":"48.8544693",
  "lng":"2.33814",
  "address":"33 Rue Mazarinne 75001 Paris",
  "pins": ["lebonbon","rock"],
  "picture":"https://fbcdn-profile-a.akamaihd.net/static-ak/rsrc.php/v2/yW/r/U2hFrus9i5v.png"
},
 {
  "name":"Établi",
  "id":"347327621972205",
  "lat":"48.8559303",
  "lng":"2.38293",
  "address":"158 bd Voltaire 75011 Paris",
  "pins": ["rock","lebonbon"],
  "picture":"https://scontent.xx.fbcdn.net/hprofile-xaf1/v/t1.0-1/c24.13.166.166/s50x50/529837_396833807021586_1525508182_n.jpg?oh=2a323cc2ae991c1d348f17d1f1c786ec&oe=5673DDED"
},
 {
  "name":"Etna",
  "id":"129234385438",
  "lat":"48.8136787",
  "lng":"2.3926001",
  "address":"15 rue Maurice Grandcoing 94200 Ivry-sur-Seine",
  "pins": ["terrasse","rock"],
  "picture":"https://fbcdn-profile-a.akamaihd.net/hprofile-ak-xpt1/v/t1.0-1/p50x50/11034917_10153201910085439_3105302316094685397_n.jpg?oh=377ee07fe6b76b18355f7f3fa87cd350&oe=567EAB7C&__gda__=1450016513_2d4f7d1c38df4744162edbc679359634"
},
 {
  "name":"Express de Lyon",
  "id":"250206515102179",
  "lat":"48.8473587",
  "lng":"2.3719201",
  "address":"10, rue de Lyon 75012 Paris",
  "pins": ["rock","bieres"],
  "picture":"https://fbcdn-profile-a.akamaihd.net/hprofile-ak-xap1/v/t1.0-1/p50x50/10407768_601779199944907_606918196755736647_n.png?oh=ffc7a8e376d97290095b901e750c108b&oe=56712192&__gda__=1449911600_2c87a3691ce550d51cb5f2af16d69892"
},
 {
  "name":"Faust",
  "id":"1440884839498361",
  "lat":"48.8632016005",
  "lng":"2.31280223635",
  "address":"Pont Alexandre III 75007 Paris",
  "pins": ["lebonbon","rock"],
  "picture":"https://fbcdn-profile-a.akamaihd.net/hprofile-ak-xpa1/v/t1.0-1/p50x50/11133822_1579588815627962_2944972477132083621_n.jpg?oh=1935acd78a81670029ffc3a79449764c&oe=567970D1&__gda__=1449023214_aadc94312da1d2924e831c7a589705ff"
},
 {
  "name":"Feeling",
  "id":"1374824759494854",
  "lat":"48.8798218",
  "lng":"2.3215201",
  "address":"61 Rue de Rome 75008 Paris",
  "pins": ["rock","lebonbon"],
  "picture":"https://fbcdn-profile-a.akamaihd.net/hprofile-ak-xpa1/v/t1.0-1/c11.0.50.50/p50x50/1510625_1374829526161044_2527567251022717152_n.jpg?oh=395c140872a9fd70ba3fa014461f1ddf&oe=568066FC&__gda__=1449145365_fc034e37912228bcc03a76e77fc21504"
},
 {
  "name":"Féline",
  "id":"259376990774354",
  "lat":"48.8671417",
  "lng":"2.3852601",
  "address":"6 rue victor letalle 75020 Paris",
  "pins": ["rock","lebonbon"],
  "picture":"https://fbcdn-profile-a.akamaihd.net/hprofile-ak-xap1/v/t1.0-1/c10.0.50.50/p50x50/1378875_652721808106535_1978397126_n.jpg?oh=046a5a829731b3125430a4fe977a90bf&oe=56A9D887&__gda__=1449242242_d7e8012a50c2c38a9198301770688b6c"
},
 {
  "name":"Festin Nu",
  "id":"467850496603700",
  "lat":"48.8904959536",
  "lng":"2.33921617631",
  "address":"10 rue de la Fontaine du But 75018 Paris",
  "pins": ["rock","lebonbon"],
  "picture":"https://scontent.xx.fbcdn.net/hprofile-xat1/v/t1.0-1/c66.66.828.828/s50x50/21103_489180407804042_292266060_n.jpg?oh=ca43545a8cf5e8ecd55b80b2e7155b24&oe=566DFC78"
},
 {
  "name":"Ficelle",
  "id":"283590018449709",
  "lat":"48.8473091",
  "lng":"2.2981999",
  "address":"16 rue Frémicourt 75015 Paris",
  "pins": ["rock","lebonbon"],
  "picture":"https://scontent.xx.fbcdn.net/hprofile-frc3/v/t1.0-1/p50x50/1425532_316389051836472_1157301891_n.jpg?oh=ca47bfcb36850fa781482ef84d4e7c7b&oe=5668C1E1"
},
 {
  "name":"Finnegans Wake",
  "id":"1425741797641730",
  "lat":"48.8458214",
  "lng":"2.35394",
  "address":"9, rue des boulangers 75005 Paris",
  "pins": ["rock","lebonbon"],
  "picture":"https://scontent.xx.fbcdn.net/hprofile-xap1/v/t1.0-1/c42.0.50.50/p50x50/1375841_1426058697610040_1155963590_n.jpg?oh=21f6880b5a148b78ec08007fc4698542&oe=566826D4"
},
 {
  "name":"Fish Club",
  "id":"451233414968795",
  "lat":"48.8639603",
  "lng":"2.3435099",
  "address":"58, rue Jean Jacques ROUSSEAU 75001 Paris",
  "pins": ["terrasse","rock"],
  "picture":"https://fbcdn-profile-a.akamaihd.net/hprofile-ak-xpf1/v/t1.0-1/p50x50/10981917_785835964841870_907453785868909822_n.png?oh=eb1df94c5589103d698be58a45e81a3e&oe=56A95F13&__gda__=1453893743_f88ebc100ca4a9f6e091bb70d6035c2d"
},
 {
  "name":"Flûte Bar Etoile",
  "id":"106368493746",
  "lat":"48.8775711",
  "lng":"2.29497",
  "address":"19 rue de l'Etoile 75017 Paris",
  "pins": ["timeout","rock"],
  "picture":"https://fbcdn-profile-a.akamaihd.net/hprofile-ak-xpf1/t5.0-1/50286_106368493746_5666336_q.jpg"
},
 {
  "name":"Footsie",
  "id":"148253441883496",
  "lat":"48.8694611",
  "lng":"2.3319199",
  "address":"10 Rue Daunou 75002 Paris",
  "pins": ["rock","terrasse"],
  "picture":"https://fbcdn-profile-a.akamaihd.net/static-ak/rsrc.php/v2/yW/r/U2hFrus9i5v.png"
},
 {
  "name":"Fourbi",
  "id":"608063365883040",
  "lat":"48.8562813",
  "lng":"2.30741",
  "address":"25 bis rue duvivier 75007 Paris",
  "pins": ["rock","terrasse"],
  "picture":"https://fbcdn-profile-a.akamaihd.net/hprofile-ak-xpa1/v/t1.0-1/c30.0.50.50/p50x50/1601196_678487055507337_1039152_n.jpg?oh=2faad7d95da23dfa02363b76a8958e20&oe=566CD152&__gda__=1450005121_560dc15ca3182c0f1e99c8c853bdf58c"
},
 {
  "name":"Fourmi",
  "id":"161609657184625",
  "lat":"48.8825417",
  "lng":"2.3397501",
  "address":"74 Rue des Martyrs 75018 Paris",
  "pins": ["bieres","rock"],
  "picture":"https://fbcdn-profile-a.akamaihd.net/hprofile-ak-xfa1/t5.0-1/1086914_161609657184625_2040052737_q.jpg"
},
 {
  "name":"French Flair",
  "id":"157688594275495",
  "lat":"48.8843525431",
  "lng":"2.33057123465",
  "address":"75 Bis bd de Clichy 75009 Paris",
  "pins": ["rock","timeout"],
  "picture":"https://fbcdn-profile-a.akamaihd.net/hprofile-ak-xfa1/v/t1.0-1/p50x50/1377096_639954439382239_1690074666_n.jpg?oh=ee2ae106f40f9aceca6ac849dd48bdd5&oe=566ABB4E&__gda__=1448996410_822f96ec81e69f5fa0e48bc91d98a1de"
},
 {
  "name":"Frenchie Bar à Vin",
  "id":"599546870172931",
  "lat":"48.8676491",
  "lng":"2.34761",
  "address":"9, rue du Nil 75002 Paris",
  "pins": ["rock","bieres"],
  "picture":"https://scontent.xx.fbcdn.net/hprofile-xap1/v/t1.0-1/c12.0.50.50/p50x50/1478988_652500974877520_2237638803513581964_n.jpg?oh=85d1ca16acfed38ba4e2db1404807038&oe=56AAD69E"
},
 {
  "name":"Frog & Rosbif",
  "id":"122262581185929",
  "lat":"48.864399",
  "lng":"2.35026",
  "address":"116, rue St Denis 75002 Paris",
  "pins": ["rock","timeout"],
  "picture":"https://fbcdn-profile-a.akamaihd.net/hprofile-ak-xap1/v/t1.0-1/p50x50/11425152_857495547662625_888000730475923146_n.jpg?oh=5775e21ffa1e2b61660610ba6fa725f4&oe=56A8B886&__gda__=1453981476_2fc25e32b18d3070783d67ebfc71986e"
},
 {
  "name":"Frog at Bercy Village",
  "id":"146115492097645",
  "lat":"48.8329697",
  "lng":"2.38622",
  "address":"25, Cour St-Emilion 75012 Paris",
  "pins": ["rock","timeout"],
  "picture":"https://fbcdn-profile-a.akamaihd.net/hprofile-ak-xpf1/v/t1.0-1/p50x50/1545995_972996142742905_1238447429706178833_n.jpg?oh=6b7c801f7b46fab43a78aaaa16b00e64&oe=565D0C04&__gda__=1449867896_984079ad4b186e706d7f885bb7bf61b5"
},
 {
  "name":"Frog XVI",
  "id":"122567411130977",
  "lat":"48.8647919",
  "lng":"2.28825",
  "address":"110 bis avenue Kléber Paris 75016 Paris",
  "pins": ["bieres","rock"],
  "picture":"https://fbcdn-profile-a.akamaihd.net/hprofile-ak-xpf1/v/t1.0-1/p50x50/1509179_835766959811015_6603448743906115140_n.jpg?oh=658a592ac415b8e577337bf10967de2d&oe=565F9920&__gda__=1450870108_704849dcebe5d9eadbd61d7ef2d72564"
},
 {
  "name":"Gibus",
  "id":"902006973196538",
  "lat":"48.868309",
  "lng":"2.3660901",
  "address":"18 rue du Faubourg du Temple 75011 Paris",
  "pins": ["rock","timeout"],
  "picture":"https://scontent.xx.fbcdn.net/hprofile-xpf1/v/t1.0-1/p50x50/1467393_914204191976816_5694252113659090894_n.jpg?oh=6b0597ad60146800a7876bd2cea52945&oe=566387F0"
},
 {
  "name":"Gibus Café",
  "id":"157066294356632",
  "lat":"48.8669205",
  "lng":"2.3761301",
  "address":"127 rue Saint Maur 75011 Paris",
  "pins": ["timeout","rock"],
  "picture":"https://fbcdn-profile-a.akamaihd.net/hprofile-ak-xpf1/v/t1.0-1/c2.0.50.50/p50x50/10978531_841958155867439_6590119955460339285_n.jpg?oh=98b547d76f7cb5c38e72d878c3af002b&oe=567E335C&__gda__=1449950473_30f9b52e1cb3b27e0a7dd90932f48690"
},
 {
  "name":"Grand Bouillon",
  "id":"1476644442551004",
  "lat":"48.9146884965",
  "lng":"2.38291132668",
  "address":"2 ter rue du Moutier 93300 Aubervilliers",
  "pins": ["rock","timeout"],
  "picture":"https://fbcdn-profile-a.akamaihd.net/hprofile-ak-xft1/v/t1.0-1/p50x50/10309194_1547906098758171_3799469825941783535_n.jpg?oh=c8cbdd9c63505f90427df44313d93f97&oe=565E3468&__gda__=1450166047_a2e178e8014c39039875f358324906ea"
},
 {
  "name":"Green Goose",
  "id":"224515764422038",
  "lat":"48.8503637107",
  "lng":"2.39062771432",
  "address":"19 rue des Boulets, 75011 75011 Paris",
  "pins": ["rock","timeout"],
  "picture":"https://fbcdn-profile-a.akamaihd.net/static-ak/rsrc.php/v2/yW/r/U2hFrus9i5v.png"
},
 {
  "name":"Grosse Caisse",
  "id":"132080850174895",
  "lat":"48.8701782",
  "lng":"2.34284",
  "address":"160 rue Montmartre 75002 Paris",
  "pins": ["terrasse","rock"],
  "picture":"https://fbcdn-profile-a.akamaihd.net/static-ak/rsrc.php/v2/yW/r/U2hFrus9i5v.png"
},
 {
  "name":"Ground Control #2",
  "id":"644196098997516",
  "lat":"48.8910408",
  "lng":"2.3529601",
  "address":"26 ter rue Ordener 75018 Paris",
  "pins": ["lebonbon","rock"],
  "picture":"https://scontent.xx.fbcdn.net/hprofile-xpt1/v/t1.0-1/p50x50/11156419_815280145222443_7282841609331765609_n.jpg?oh=42d7fb28496db599ee42ee909d4fb1f5&oe=56674B86"
},
 {
  "name":"Guepe",
  "id":"428388220552808",
  "lat":"48.8844843342",
  "lng":"2.34121013488",
  "address":"14 rue des Trois Frères 75018 Paris",
  "pins": ["rock","lebonbon"],
  "picture":"https://fbcdn-profile-a.akamaihd.net/hprofile-ak-xfa1/v/t1.0-1/c44.44.549.549/s50x50/550643_428399310551699_1683475790_n.jpg?oh=804ef7794ab12f918765771b34df83c3&oe=5666FDF3&__gda__=1449470659_74d65a34cf666caa828374f3974fe34c"
},
 {
  "name":"Gueuze",
  "id":"288651131206719",
  "lat":"48.8472753808",
  "lng":"2.34141678367",
  "address":"19 rue soufflot 75005 Paris",
  "pins": ["bieres","rock"],
  "picture":"https://fbcdn-profile-a.akamaihd.net/hprofile-ak-xfa1/v/t1.0-1/c113.33.414.414/s50x50/429874_288654507873048_400083695_n.jpg?oh=48f65dc9d7f7359894ecf1b943f660ca&oe=56663606&__gda__=1449586998_b1c6f55ee3b0424c1af40ec98b52fa94"
},
 {
  "name":"Harry's Bar",
  "id":"148282981897528",
  "lat":"48.8692589",
  "lng":"2.3320999",
  "address":"5 rue Daunou 75002 Paris",
  "pins": ["rock","lebonbon"],
  "picture":"https://fbcdn-profile-a.akamaihd.net/hprofile-ak-xfp1/v/t1.0-1/p50x50/10888630_862473307145155_7333989508063501414_n.jpg?oh=9767bd6989e685495664da8dae3808e5&oe=56712F99&__gda__=1451163903_ef586ac9b42e6a9250dbc9eb8c589002"
},
 {
  "name":"Hôtel Cinq Codet",
  "id":"270498176449749",
  "lat":"48.8549881",
  "lng":"2.3083501",
  "address":"5 rue louis codet 75007 Paris",
  "pins": ["rock","timeout"],
  "picture":"https://fbcdn-profile-a.akamaihd.net/hprofile-ak-xtp1/v/t1.0-1/p50x50/1545821_270498743116359_1235960941_n.png?oh=9caab4e321834cf716a59f61de5a4675&oe=567A328F&__gda__=1450328123_287580f64bd6dd4556af08c0b4ea44ef"
},
 {
  "name":"Hypnose Bar",
  "id":"462168340564752",
  "lat":"48.8512346299",
  "lng":"2.33933021759",
  "address":"rue monsieur le prince  75006 Paris",
  "pins": ["terrasse","rock"],
  "picture":"https://fbcdn-profile-a.akamaihd.net/static-ak/rsrc.php/v2/y5/r/j258ei8TIHu.png"
},
 {
  "name":"Jamon Jamon",
  "id":"1571372489797240",
  "lat":"48.8678284",
  "lng":"2.3550999",
  "address":"310 Rue Saint-Martin 75003 Paris",
  "pins": ["terrasse","rock"],
  "picture":"https://fbcdn-profile-a.akamaihd.net/hprofile-ak-xfa1/v/t1.0-1/p50x50/644449_1571684566432699_830987556278711861_n.jpg?oh=43dd0d56e7f459228c783c400b899e36&oe=567309AD&__gda__=1450513408_d45bd24d4aebb6ff8ab805f1f779b49b"
},
 {
  "name":"Jardin Français",
  "id":"699989596683375",
  "lat":"48.8716812",
  "lng":"2.31476",
  "address":"112 rue du Faubourg Saint Honoré 75008 Paris",
  "pins": ["rock","timeout"],
  "picture":"https://fbcdn-profile-a.akamaihd.net/static-ak/rsrc.php/v2/yW/r/U2hFrus9i5v.png"
},
 {
  "name":"Javelle",
  "id":"524772137649552",
  "lat":"48.8411570052",
  "lng":"2.27072035124",
  "address":"Port Javel Bas  75015 Paris",
  "pins": ["lebonbon","rock"],
  "picture":"https://fbcdn-profile-a.akamaihd.net/hprofile-ak-xpa1/v/t1.0-1/c3.0.50.50/p50x50/11707555_738667052926725_353350203347510338_n.png?oh=bd8f7e4fb4d3e41f56c53289a620459c&oe=566EAC9A&__gda__=1449897565_8856fd365b1ec61466bf9d18a5fd7250"
},
 {
  "name":"K1ZE",
  "id":"119549501438584",
  "lat":"48.8686714",
  "lng":"2.3341899",
  "address":"15 rue gaillon 75002 Paris",
  "pins": ["rock","timeout"],
  "picture":"https://fbcdn-profile-a.akamaihd.net/hprofile-ak-xfp1/v/t1.0-1/c0.0.50.50/p50x50/1375064_595033967223466_587189594_n.jpg?oh=522c4e21c7282a00faa40774878accdb&oe=565FC79A&__gda__=1454047740_29bc48507c8535ffd078375c4b12954f"
},
 {
  "name":"Kiez Biergarten",
  "id":"745766438802154",
  "lat":"48.8935814",
  "lng":"2.3333001",
  "address":"24 rue Vauvenargues 75018 Paris",
  "pins": ["timeout","rock"],
  "picture":"https://fbcdn-profile-a.akamaihd.net/hprofile-ak-xfp1/v/t1.0-1/c0.0.50.50/p50x50/10702100_814899098555554_7791320490096585652_n.png?oh=094c454fd4398ed3acc68fd20fe3151e&oe=565F7155&__gda__=1450881137_cac1955a9111f195f1b72c632df6e902"
},
 {
  "name":"L'Ambre",
  "id":"154480798025637",
  "lat":"48.8786507",
  "lng":"2.2876401",
  "address":"29 Rue Brunel 75017 Paris",
  "pins": ["rock","lebonbon"],
  "picture":"https://scontent.xx.fbcdn.net/hprofile-xpa1/v/l/t1.0-1/c2.0.50.50/p50x50/1425568_1431733430300361_13825179_n.jpg?oh=2f50cc7744b638c8c6ffa4dbe4b6eeac&oe=567A1F89"
},
 {
  "name":"L'Andy Wahloo",
  "id":"498777960154651",
  "lat":"48.8645096",
  "lng":"2.3542299",
  "address":"69 rue des gravilliers 75003 Paris",
  "pins": ["lebonbon","rock"],
  "picture":"https://scontent.xx.fbcdn.net/hprofile-xfa1/v/t1.0-1/c0.8.50.50/p50x50/318080_515796948452752_1082659197_n.png?oh=d4ab7471c5e3fb65fc386465b6b3a540&oe=567704A5"
},
 {
  "name":"L'Âne Chic",
  "id":"786526098046239",
  "lat":"48.8737907",
  "lng":"2.3503201",
  "address":"37 bis, Rue des Petites Ecuries 75010 Paris",
  "pins": ["rock","lebonbon"],
  "picture":"https://scontent.xx.fbcdn.net/hprofile-xat1/v/t1.0-1/p50x50/10308084_787012984664217_6654614123167298406_n.png?oh=9b3352a580095df5f7619ff58eec05b5&oe=567FC3A3"
},
 {
  "name":"L'Atelier des Artistes",
  "id":"504221593026571",
  "lat":"48.8727493",
  "lng":"2.44016",
  "address":"73 Boulevard Edouard Branly 93230 Romainville",
  "pins": ["timeout","rock"],
  "picture":"https://scontent.xx.fbcdn.net/hprofile-xap1/v/t1.0-1/c8.0.50.50/p50x50/10599186_613892132059516_8489928710364292170_n.jpg?oh=0fd5ddb152be42d70d72dcd70b10abf9&oe=567D51BC"
},
 {
  "name":"l'Atelier Renault",
  "id":"117447518303977",
  "lat":"48.8704130263",
  "lng":"2.30561899534",
  "address":"53 avenue des Champs-Elysées 75008 Paris",
  "pins": ["rock","timeout"],
  "picture":"https://fbcdn-profile-a.akamaihd.net/hprofile-ak-xfa1/v/t1.0-1/c41.41.517.517/s50x50/429606_317992594916134_1049797449_n.jpg?oh=b4fbae65f994d6fa53eca80596e54a7c&oe=567723E1&__gda__=1451136465_8882f62f17835a0c93d1b480cd9a34c5"
},
 {
  "name":"L'Éléphant du Nil",
  "id":"703180429771028",
  "lat":"48.8551598",
  "lng":"2.36022",
  "address":"125 Rue Saint-Antoine 75004 Paris",
  "pins": ["timeout","rock"],
  "picture":"https://fbcdn-profile-a.akamaihd.net/hprofile-ak-xfa1/v/t1.0-1/p50x50/11164727_815912085164528_2209252581316946485_n.jpg?oh=125240bc8ad9055da419c6b7c620e305&oe=566A2E24&__gda__=1448950644_cf86ecb303b00542823d61010df9da8e"
},
 {
  "name":"L'Embuscade",
  "id":"312211212176898",
  "lat":"48.8646202",
  "lng":"2.36957",
  "address":"31,rue de Crussol 75011 Paris",
  "pins": ["rock","timeout"],
  "picture":"https://fbcdn-profile-a.akamaihd.net/hprofile-ak-xfa1/v/t1.0-1/c15.15.188.188/s50x50/405074_347877778610241_1661603024_n.jpg?oh=9107cd3bf3d6a27b8d5467fa6a88012d&oe=567B40FB&__gda__=1450758091_e7ab9e2285224ba58d8c3a9f21193795"
},
 {
  "name":"L'Entrée des Artistes",
  "id":"835878193137735",
  "lat":"48.8639603",
  "lng":"2.36747",
  "address":"8 rue de Crussol 75011 Paris",
  "pins": ["rock","terrasse"],
  "picture":"https://scontent.xx.fbcdn.net/hprofile-xpt1/v/t1.0-1/c11.0.50.50/p50x50/10919062_890092297716324_3497138219627076761_n.jpg?oh=69dc345ac419014a669a53949ed3ae5d&oe=56724605"
},
 {
  "name":"L'épicerie Saint Sabin",
  "id":"230191067125528",
  "lat":"48.855280382",
  "lng":"2.37194721505",
  "address":"13, rue Saint Sabin 75011 Paris",
  "pins": ["bieres","rock"],
  "picture":"https://scontent.xx.fbcdn.net/hprofile-xpa1/v/t1.0-1/c0.0.50.50/p50x50/1374787_332584763552824_231988873_n.png?oh=c5a7c14b82eaf36d4787167de5d1e80e&oe=5671DBAA"
},
 {
  "name":"L'Orillon Bar",
  "id":"341368692625875",
  "lat":"48.8702507",
  "lng":"2.3763101",
  "address":"35 rue de l'Orillon 75011 Paris",
  "pins": ["timeout","rock"],
  "picture":"https://scontent.xx.fbcdn.net/hprofile-xpf1/v/t1.0-1/c0.0.50.50/p50x50/11014668_788275417935198_7536282728938452536_n.jpg?oh=119d5d6103f885047783f77b4cc3cc66&oe=56701595"
},
 {
  "name":"L'Ours Bar",
  "id":"223653451134437",
  "lat":"48.8745995",
  "lng":"2.3545001",
  "address":"8 rue de Paradis 75010 Paris",
  "pins": ["rock","lebonbon"],
  "picture":"https://scontent.xx.fbcdn.net/hprofile-xpa1/v/t1.0-1/p50x50/1385374_224610211038761_377638676_n.jpg?oh=f335eb6ebc3a80141f6a487e09a05371&oe=56656841"
},
 {
  "name":"L’Ours Bar",
  "id":"223653451134437",
  "lat":"48.8745995",
  "lng":"2.3545001",
  "address":"8 rue de Paradis 75010 Paris",
  "pins": ["lebonbon","rock"],
  "picture":"https://scontent.xx.fbcdn.net/hprofile-xpa1/v/t1.0-1/p50x50/1385374_224610211038761_377638676_n.jpg?oh=f335eb6ebc3a80141f6a487e09a05371&oe=56656841"
},
 {
  "name":"la Serena",
  "id":"150800291624466",
  "lat":"48.8703308",
  "lng":"2.33936",
  "address":"92 rue de Richelieu 75002 Paris",
  "pins": ["rock"],
  "picture":"https://fbcdn-profile-a.akamaihd.net/hprofile-ak-xfp1/v/t1.0-1/c5.0.50.50/p50x50/994488_728757970495359_5257926638066433173_n.jpg?oh=cdea449528712cd0656dc8aa2d77cab9&oe=567810C8&__gda__=1449771599_dcb4a0d404a9ab8deac728dd842d5d15"
},
 {
  "name":"le Pershing Hall",
  "id":"51886409972",
  "lat":"48.8690853203",
  "lng":"2.30220004079",
  "address":"49 Rue Pierre Charron 75008 Paris",
  "pins": ["rock"],
  "picture":"https://scontent.xx.fbcdn.net/hprofile-xfa1/v/t1.0-1/c0.0.50.50/p50x50/1384215_10152028247139973_143454530_n.jpg?oh=5433c464a8b8a3981411d5028d5adfe2&oe=567EFDC9"
},
 {
  "name":"Les Dégommés",
  "id":"246078022194815",
  "lat":"48.8663597",
  "lng":"2.37993",
  "address":"131, rue oberkampf 75011 Paris",
  "pins": ["rock"],
  "picture":"https://fbcdn-profile-a.akamaihd.net/hprofile-ak-xap1/v/t1.0-1/p50x50/58676_344604795675470_915429907_n.jpg?oh=a042ead51e439e0c2a615140b6866edf&oe=567AB3CF&__gda__=1454101622_cace22dcdfb1099bc623f20e64fe1f15"
},
 {
  "name":"Les Souffleurs",
  "id":"133452263368348",
  "lat":"48.8568611",
  "lng":"2.3554399",
  "address":"7, rue de la verrerie 75004 Paris",
  "pins": ["rock"],
  "picture":"https://scontent.xx.fbcdn.net/hprofile-xaf1/v/t1.0-1/c0.7.50.50/p50x50/10414413_739124982801070_2455416948555525321_n.jpg?oh=12ac76541f22e0578612c72948d06948&oe=567D0C57"
},
 {
  "name":"Lulu White",
  "id":"380334005424995",
  "lat":"48.881649",
  "lng":"2.33745",
  "address":"12 Rue Frochot 75009 Paris",
  "pins": ["rock"],
  "picture":"https://fbcdn-profile-a.akamaihd.net/hprofile-ak-xpf1/v/t1.0-1/p50x50/11873416_452014124923649_2010424318995896247_n.jpg?oh=7327b1a2345d1472ffb2a36589aeca01&oe=56674553&__gda__=1451025912_27ccb6adfa4b12d19bb1c6dab91ec51f"
},
 {
  "name":"Ma Cave Fleury",
  "id":"137640196306835",
  "lat":"48.8655281",
  "lng":"2.35043",
  "address":"177 rue Saint Denis 75002 Paris",
  "pins": ["rock"],
  "picture":"https://fbcdn-profile-a.akamaihd.net/hprofile-ak-xaf1/v/t1.0-1/p50x50/10277750_10152471825399561_3678397178295353159_n.jpg?oh=769cfa42755836561f3734af47270667&oe=56685143&__gda__=1449254911_79633dc039193e7ec6c16a443f78ad48"
},
 {
  "name":"Madam",
  "id":"132051993532994",
  "lat":"48.8713041573",
  "lng":"2.36284761988",
  "address":"Rue des Récollets 75010 Paris",
  "pins": ["rock"],
  "picture":"https://scontent.xx.fbcdn.net/hprofile-xpa1/v/t1.0-1/p50x50/10336852_10152054747282001_3686348613081552146_n.jpg?oh=cfb3f08efc31ab09f61aacc2572f5634&oe=56A8B189"
},
 {
  "name":"Mama Shelter",
  "id":"152836168081344",
  "lat":"48.8597299",
  "lng":"2.4028899",
  "address":"empty",
  "pins": ["rock"],
  "picture":"https://fbcdn-profile-a.akamaihd.net/hprofile-ak-xap1/v/t1.0-1/p50x50/1469743_854171981281089_6212285768488197384_n.png?oh=76bcd9cdcb67a3cca539d4b78fa8faad&oe=565F4A15&__gda__=1449392311_623845cb99adf6fe56e2148688d5be4c"
},
 {
  "name":"Marilyn",
  "id":"1072109919473784",
  "lat":"48.8645515",
  "lng":"2.3505299",
  "address":"17 passage du bourg l'abbé  75002 Paris",
  "pins": ["rock"],
  "picture":"https://fbcdn-profile-a.akamaihd.net/static-ak/rsrc.php/v2/y5/r/j258ei8TIHu.png"
},
 {
  "name":"Mary Celeste",
  "id":"396980953716490",
  "lat":"48.8618160629",
  "lng":"2.36499262493",
  "address":"1, Rue Commines 75003 Paris",
  "pins": ["rock"],
  "picture":"https://scontent.xx.fbcdn.net/hprofile-ash2/v/t1.0-1/c0.14.50.50/p50x50/1393749_534335693314348_536400418_n.jpg?oh=5d855238d9e0d4a0002919a728cd9370&oe=5672455C"
},
 {
  "name":"Miss Kô",
  "id":"295312367244937",
  "lat":"48.8708992",
  "lng":"2.3006301",
  "address":"49/51 avenue George V 75008 Paris",
  "pins": ["rock"],
  "picture":"https://fbcdn-profile-a.akamaihd.net/hprofile-ak-xat1/v/t1.0-1/c0.11.50.50/p50x50/1503941_515012178608287_1993923605_n.jpg?oh=d086e4e3ea66201a87cbdf60b39c06f4&oe=56ABCD6E&__gda__=1450288201_373fb64874315967d42a1abc3062af29"
},
 {
  "name":"Moka Goncourt",
  "id":"1498142413758645",
  "lat":"48.8701591",
  "lng":"2.3713",
  "address":"75 rue du faubourg du temple 75010 Paris",
  "pins": ["rock"],
  "picture":"https://fbcdn-profile-a.akamaihd.net/static-ak/rsrc.php/v2/yW/r/U2hFrus9i5v.png"
},
 {
  "name":"Montana",
  "id":"1402451980072327",
  "lat":"48.8541985",
  "lng":"2.33269",
  "address":"28 Rue Saint-Benoît,  75006 Paris",
  "pins": ["timeout","rock"],
  "picture":"https://scontent.xx.fbcdn.net/hprofile-xlt1/v/t1.0-1/c5.0.50.50/p50x50/11221343_1497326377251553_46860946137825797_n.jpg?oh=8f7174e6fb0da57d9e477436c90a56f5&oe=567A6A2E"
},
 {
  "name":"Mood",
  "id":"115453138484108",
  "lat":"48.8721886",
  "lng":"2.3011701",
  "address":"114 avenue des Champs Elysées 75008 Paris",
  "pins": ["rock","lebonbon"],
  "picture":"https://scontent.xx.fbcdn.net/hprofile-xfa1/v/t1.0-1/c28.28.347.347/s50x50/545962_405872936108792_165781799_n.jpg?oh=107185c467519634143f2ea2e4cafcb8&oe=566BE11F"
},
 {
  "name":"Mordant",
  "id":"1515808582032423",
  "lat":"48.8770905",
  "lng":"2.3510101",
  "address":"61 rue de Chabrol / Paris X 75010 Paris",
  "pins": ["lebonbon","rock"],
  "picture":"https://scontent.xx.fbcdn.net/hprofile-xtp1/v/t1.0-1/p50x50/11536070_1585777935035487_2938445336600829456_n.jpg?oh=3c3deda6ce0b89025f3a58174f9502bd&oe=567F63EB"
},
 {
  "name":"Nakatani",
  "id":"1480074028942608",
  "lat":"48.8491783",
  "lng":"2.3191199",
  "address":"Rue Pierre Leroux  75007 Paris",
  "pins": ["rock"],
  "picture":"https://fbcdn-profile-a.akamaihd.net/static-ak/rsrc.php/v2/yW/r/U2hFrus9i5v.png"
},
 {
  "name":"Nul Bar Ailleurs",
  "id":"123009531093588",
  "lat":"48.8499107",
  "lng":"2.3780899",
  "address":"18 rue de cotte 75012 Paris",
  "pins": ["timeout","rock"],
  "picture":"https://fbcdn-profile-a.akamaihd.net/hprofile-ak-xpf1/v/t1.0-1/p50x50/11828804_925246874203179_4231910039089700224_n.jpg?oh=b22ae8a302a02968fc0653947b951560&oe=567FC354&__gda__=1449630975_0b32e23c6c8593f54879e764a6886dd2"
},
 {
  "name":"Ô Chateau",
  "id":"163527813648",
  "lat":"48.8643188",
  "lng":"2.3442099",
  "address":"68 Rue Jean Jacques Rousseau 75001 Paris",
  "pins": ["rock","lebonbon"],
  "picture":"https://scontent.xx.fbcdn.net/hprofile-xaf1/v/t1.0-1/c51.30.640.640/s50x50/574944_10150707565098649_920041216_n.jpg?oh=4580dfe1c865ee283c0307a3c8e44172&oe=5669A0A6"
},
 {
  "name":"O'neil",
  "id":"50194981491",
  "lat":"48.8518486",
  "lng":"2.3336599",
  "address":"20 Rue des Canettes 75006 Paris",
  "pins": ["lebonbon","rock"],
  "picture":"https://fbcdn-profile-a.akamaihd.net/hprofile-ak-xfp1/v/t1.0-1/c0.0.50.50/p50x50/11057451_10153205555296492_7129823519448712007_n.jpg?oh=4230b63461446a43dbd956b14ef19f27&oe=56AA07E8&__gda__=1450623006_adc9c9daf2a24160779f5fa1a55d1f8b"
},
 {
  "name":"Odette et Aimé",
  "id":"112553392139581",
  "lat":"48.8783684",
  "lng":"2.3454001",
  "address":"46 Rue de Maubeuge 75009 Paris",
  "pins": ["rock"],
  "picture":"https://fbcdn-profile-a.akamaihd.net/hprofile-ak-frc3/v/t1.0-1/p50x50/62322_1453828191510836_77450503_n.jpg?oh=43d185ae2264dc32797d5c2c14d209fd&oe=566446F3&__gda__=1450060617_8df730c53d2e496f9a5c65c396fb08c7"
},
 {
  "name":"Paname Art Café",
  "id":"179136575450724",
  "lat":"48.8683891",
  "lng":"2.3699701",
  "address":"14, rue de la fontaine au Roi 75011 Paris",
  "pins": ["timeout","rock"],
  "picture":"https://scontent.xx.fbcdn.net/hprofile-xtp1/v/t1.0-1/p50x50/1688061_701439303220446_479297383_n.jpg?oh=e17df7c1372729fcfe4dbf234a45cf76&oe=566C23A2"
},
 {
  "name":"Paname Brewing Company",
  "id":"552467018217562",
  "lat":"48.8877110056",
  "lng":"2.37864732742",
  "address":"41 Quai de la Loire 75019 Paris",
  "pins": ["rock","lebonbon"],
  "picture":"https://fbcdn-profile-a.akamaihd.net/hprofile-ak-xpf1/v/t1.0-1/c12.0.50.50/p50x50/16230_601663373297926_6733912258901884814_n.jpg?oh=01a9b7bd5336619dcefa442343c35960&oe=567CD8C5&__gda__=1449007735_f1431b076665122a539a4100f9cef4a6"
},
 {
  "name":"PanPan",
  "id":"714519175303850",
  "lat":"48.8747675086",
  "lng":"2.34091976703",
  "address":"32, rue Drouot 75009 Paris",
  "pins": ["lebonbon","rock"],
  "picture":"https://fbcdn-profile-a.akamaihd.net/hprofile-ak-xpf1/v/t1.0-1/p50x50/10418913_716689975086770_2968778487149833044_n.jpg?oh=6c57fcbf44b0d7af8143f89842fc0466&oe=5676D18B&__gda__=1453894944_4469f31b264b7d969b5b57e566f08f42"
},
 {
  "name":"Park Hyatt Paris",
  "id":"147939888581759",
  "lat":"48.8688975925",
  "lng":"2.33018333257",
  "address":"5, rue de la Paix 75002 Paris",
  "pins": ["rock"],
  "picture":"https://fbcdn-profile-a.akamaihd.net/hprofile-ak-xfa1/v/t1.0-1/p50x50/10454561_746944528681289_7299162182111568321_n.jpg?oh=72fe88bf54841ae6c2554d9feff3a169&oe=567F9CB7&__gda__=1448978151_13f2c18bd21b7a648d701c0309f68f5b"
},
 {
  "name":"Peniche Baleine Blanche",
  "id":"255739071134316",
  "lat":"48.8371569113",
  "lng":"2.37487408034",
  "address":"Port de la Gare, au niveau du 85-87 quai de la Gare 75013 Paris",
  "pins": ["timeout","rock"],
  "picture":"https://fbcdn-profile-a.akamaihd.net/hprofile-ak-xpf1/v/t1.0-1/c2.0.50.50/p50x50/10615357_835288369846047_3673378258461161019_n.jpg?oh=8a6d866687a7961503c2bed1f9aa9dbf&oe=565DC55A&__gda__=1449118479_b58a53f6484554918a225ef2e665020e"
},
 {
  "name":"Penthouse Club",
  "id":"134952023290985",
  "lat":"48.8725014",
  "lng":"2.3041301",
  "address":"13/15, rue de Berri 75008 Paris",
  "pins": ["rock","lebonbon"],
  "picture":"https://fbcdn-profile-a.akamaihd.net/hprofile-ak-ash2/v/t1.0-1/c106.51.635.635/s50x50/546961_307204126065773_324032782_n.png?oh=e641f627ee785aab9a65029ef02e6e18&oe=56676038&__gda__=1450908010_1304a34f984d096481a2ecd0dcf8accd"
},
 {
  "name":"Pèpère Jean",
  "id":"487534891265266",
  "lat":"48.8678191705",
  "lng":"2.34355679242",
  "address":"3, rue Paul Lelong 75002 Paris",
  "pins": ["lebonbon","rock"],
  "picture":"https://scontent.xx.fbcdn.net/hprofile-xat1/v/t1.0-1/c0.0.50.50/p50x50/10703685_836913829660702_2379342901859838601_n.jpg?oh=6dffe8fa4788b7b1b6b8bedf446115f3&oe=56746DCC"
},
 {
  "name":"Petit Bain",
  "id":"128530333890145",
  "lat":"48.8353969784",
  "lng":"2.37678250673",
  "address":"Petit Bain, 7 port de la Gare, 75013 Paris 75013 Paris",
  "pins": ["rock"],
  "picture":"https://fbcdn-profile-a.akamaihd.net/hprofile-ak-xpf1/v/t1.0-1/c150.3.195.195/s50x50/10156069_616106485132525_1540781469_n.jpg?oh=32a6f276f1b670d47f5c68911357e12e&oe=565EEB4C&__gda__=1449525279_2dfd8d8de2f5cb6aff5c904845614fe0"
},
 {
  "name":"Petit Poucet",
  "id":"171409933062194",
  "lat":"48.8836517",
  "lng":"2.3269167",
  "address":"5 Place de Clichy 75017 Paris",
  "pins": ["timeout","rock"],
  "picture":"https://scontent.xx.fbcdn.net/hprofile-xpf1/v/t1.0-1/p50x50/996019_172038199666034_1969886478_n.jpg?oh=932e688f2563f8460f1c46a2628f7eb1&oe=5679FFEA"
},
 {
  "name":"Petit Prince de Paris",
  "id":"154364861264714",
  "lat":"48.8484612",
  "lng":"2.3464899",
  "address":"12, rue de Lanneau 75005 Paris",
  "pins": ["rock","lebonbon"],
  "picture":"https://scontent.xx.fbcdn.net/hprofile-xfa1/v/t1.0-1/c0.0.50.50/p50x50/259941_223734220994444_938191_n.jpg?oh=a7924c4d16eaf34a51796e3c5a03f871&oe=56675322"
},
 {
  "name":"Petit Village",
  "id":"495292610613620",
  "lat":"48.8712006",
  "lng":"2.3926899",
  "address":"335, Rue des Pyrénées  75020 Paris",
  "pins": ["lebonbon","rock"],
  "picture":"https://fbcdn-profile-a.akamaihd.net/hprofile-ak-xpt1/v/t1.0-1/c13.0.50.50/p50x50/11230727_591474504328763_5979574426150852020_n.jpg?oh=6016de55283904b0e49b588c4a6934e3&oe=566C92B2&__gda__=1450083792_ac4c69e4ba35449f58d735f1ac8fba4f"
},
 {
  "name":"Petite Taverne",
  "id":"198712173622692",
  "lat":"48.8806915",
  "lng":"2.33531",
  "address":"53 rue Jean-Baptiste Pigalle 75009 Paris",
  "pins": ["rock"],
  "picture":"https://scontent.xx.fbcdn.net/hprofile-xaf1/v/t1.0-1/c28.28.345.345/s50x50/1000219_198716766955566_300737973_n.jpg?oh=7d60411305dc749b305899839c38abe3&oe=567D4193"
},
 {
  "name":"Pirouette",
  "id":"670276066358472",
  "lat":"48.8618",
  "lng":"2.347169",
  "address":"5 rue Mondétour 75001 Paris",
  "pins": ["timeout","rock"],
  "picture":"https://external.xx.fbcdn.net/safe_image.php?d=AQAjKO05hoJftWpi&w=50&h=50&url=http%3A%2F%2Fupload.wikimedia.org%2Fwikipedia%2Fcommons%2Fe%2Fe3%2FRue_Pirouette_by_Charles_Meryon.jpg&crop&fallback=hub_likes&prefix=q"
},
 {
  "name":"Place Verte",
  "id":"164224590254901",
  "lat":"48.8658714",
  "lng":"2.37745",
  "address":"105 rue Oberkampf 75011 Paris",
  "pins": ["rock","lebonbon"],
  "picture":"https://fbcdn-profile-a.akamaihd.net/static-ak/rsrc.php/v2/yW/r/U2hFrus9i5v.png"
},
 {
  "name":"Playtime Cocktails",
  "id":"397323663648094",
  "lat":"48.8534698",
  "lng":"2.33606",
  "address":"34 rue de Buci 75006 Paris",
  "pins": ["lebonbon","rock"],
  "picture":"https://fbcdn-profile-a.akamaihd.net/hprofile-ak-xfa1/v/t1.0-1/c39.17.217.217/s50x50/600135_397340363646424_924887310_n.jpg?oh=932fd72d199d1df7174ee7782987e1be&oe=565DD10D&__gda__=1450261825_62efa2bf4380d244789682291d788862"
},
 {
  "name":"Polly Maggoo",
  "id":"307824537949",
  "lat":"48.8526306",
  "lng":"2.3467",
  "address":"3-5 rue du Petit Pont 75015 Paris",
  "pins": ["rock"],
  "picture":"https://fbcdn-profile-a.akamaihd.net/static-ak/rsrc.php/v2/yW/r/U2hFrus9i5v.png"
},
 {
  "name":"Poulette de Grain",
  "id":"302952473163052",
  "lat":"48.8498383",
  "lng":"2.38709",
  "address":"261, rue du faubourg Saint-Antoine 75011 Paris",
  "pins": ["timeout","lebonbon","rock"],
  "picture":"https://fbcdn-profile-a.akamaihd.net/hprofile-ak-xap1/v/t1.0-1/c0.0.50.50/p50x50/1509027_302953303162969_26088292_n.jpg?oh=6e5543cfef978719e5b183c844a24a3a&oe=566AA6B5&__gda__=1449126679_42b1fab8b0d55a1adbe7c5573329bbc6"
},
 {
  "name":"Prescription Cocktail Club",
  "id":"197589633704800",
  "lat":"48.8549539905",
  "lng":"2.33790385669",
  "address":"23 rue Mazarine 75006 Paris",
  "pins": ["terrasse","rock","lebonbon"],
  "picture":"https://fbcdn-profile-a.akamaihd.net/static-ak/rsrc.php/v2/y5/r/j258ei8TIHu.png"
},
 {
  "name":"Pure Café",
  "id":"430135693696321",
  "lat":"48.8533240533",
  "lng":"2.3831559",
  "address":"14, Rue Jean Macé 75011 Paris",
  "pins": ["rock","timeout","bieres"],
  "picture":"https://fbcdn-profile-a.akamaihd.net/hprofile-ak-xpf1/v/t1.0-1/c13.0.50.50/p50x50/11933453_947502268626325_3704836910401533418_n.jpg?oh=832cbe66c01149d8c308b07ca8f530bf&oe=567DDC28&__gda__=1449717977_e159d3ad58a0e93243d40056d473d75a"
},
 {
  "name":"Quedubon",
  "id":"193225260716269",
  "lat":"48.8781100739",
  "lng":"2.38442985266",
  "address":"22 rue du Plateau 75019 Paris",
  "pins": ["rock","timeout","terrasse"],
  "picture":"https://fbcdn-profile-a.akamaihd.net/hprofile-ak-xpf1/v/t1.0-1/p50x50/604143_10152853447564936_4713007215227368079_n.jpg?oh=e5cae16162479d5f49eee35c9f50e5d3&oe=566C3C28&__gda__=1449536899_db15e2232aa5fe77cc123b4208a1288b"
},
 {
  "name":"Quetzal",
  "id":"112828519065993",
  "lat":"48.8572311",
  "lng":"2.3551099",
  "address":"10 rue de la verrerie 75004 Paris",
  "pins": ["bieres","rock","terrasse"],
  "picture":"https://scontent.xx.fbcdn.net/hprofile-xpt1/v/t1.0-1/p50x50/11880497_112829192399259_8246310087647526030_n.jpg?oh=93dd1232e9b57dd81db646468f305c35&oe=5668BF39"
},
 {
  "name":"Quincaillerie",
  "id":"334462189939754",
  "lat":"48.8731511416",
  "lng":"2.35464594344",
  "address":"76 rue du Faubourg Saint-Denis 75010 Paris",
  "pins": ["rock","timeout","terrasse"],
  "picture":"https://fbcdn-profile-a.akamaihd.net/hprofile-ak-xpf1/v/t1.0-1/p50x50/301008_446743108711661_77071645_n.jpg?oh=c806dd544efce7ff8daea44cf5236cf5&oe=56751DBB&__gda__=1450694820_d599a0e8c06545af82023744ee4a6a10"
},
 {
  "name":"Raphaël",
  "id":"177501325651923",
  "lat":"48.8571091",
  "lng":"2.3415799",
  "address":"41 Quai de l'Horloge (Pont Neuf) 75001 Paris",
  "pins": ["rock","lebonbon","terrasse"],
  "picture":"https://fbcdn-profile-a.akamaihd.net/static-ak/rsrc.php/v2/y5/r/j258ei8TIHu.png"
},
 {
  "name":"Recyclerie",
  "id":"130357863828214",
  "lat":"48.8976517",
  "lng":"2.3441701",
  "address":"83 Boulevard Ornano 75018 Paris",
  "pins": ["timeout","lebonbon","rock"],
  "picture":"https://fbcdn-profile-a.akamaihd.net/hprofile-ak-xap1/v/t1.0-1/p50x50/486866_130360607161273_162325378_n.jpg?oh=26d5e73287ef64cd1a566c1ae708a528&oe=567BC85A&__gda__=1449735022_605b5830a480c56a578643362d93a6d8"
},
 {
  "name":"Red House",
  "id":"157254821011789",
  "lat":"48.8506088",
  "lng":"2.3801",
  "address":"1 bis rue de la forge royale 75011 Paris",
  "pins": ["rock","terrasse","timeout"],
  "picture":"https://fbcdn-profile-a.akamaihd.net/hprofile-ak-xpa1/v/t1.0-1/c16.0.50.50/p50x50/1450159_574646532605947_81158212_n.jpg?oh=f4cd5a0ed32971d08528297b4ad4bc30&oe=5675F9B1&__gda__=1451270061_f9f1a8c7fdeaf2e5f8585c57bb066201"
},
 {
  "name":"Refuge",
  "id":"328198177297539",
  "lat":"48.8899803",
  "lng":"2.3389299",
  "address":"72 rue Lamarck 75018 Paris",
  "pins": ["timeout","lebonbon","rock"],
  "picture":"https://fbcdn-profile-a.akamaihd.net/hprofile-ak-xpa1/v/t1.0-1/c66.66.828.828/s50x50/734644_328603653923658_811887955_n.jpg?oh=1e639456e079bc4b3550f52e4870c2f5&oe=566A60F4&__gda__=1449832950_6721586c3c84aad865887b022db827ce"
},
 {
  "name":"Régine's",
  "id":"110848012259875",
  "lat":"48.8718062554",
  "lng":"2.30627049154",
  "address":"49 rue de Ponthieu 75008 Paris",
  "pins": ["terrasse","rock","lebonbon"],
  "picture":"https://scontent.xx.fbcdn.net/hprofile-xap1/v/t1.0-1/p50x50/1240619_660632353948102_1582217519_n.png?oh=e31e875c84e520cb8cb35a01a2742533&oe=566BEDF0"
},
 {
  "name":"Rivolux",
  "id":"254072814724049",
  "lat":"48.8557091",
  "lng":"2.3594899",
  "address":"16 rue de Rivoli 75004 Paris",
  "pins": ["rock","timeout","bieres"],
  "picture":"https://scontent.xx.fbcdn.net/hprofile-xap1/v/t1.0-1/c31.31.388.388/s50x50/425976_271333999664597_608345723_n.jpg?oh=0c71759009645fe0a1c22594bd132215&oe=5671D4B2"
},
 {
  "name":"Rock'n Roll Circus",
  "id":"860320474012077",
  "lat":"48.8646317",
  "lng":"2.29706",
  "address":"13 avenue du président wilson 75116 Paris",
  "pins": ["rock","timeout","terrasse"],
  "picture":"https://scontent.xx.fbcdn.net/hprofile-xtf1/v/t1.0-1/c15.0.50.50/p50x50/10981798_935031336540990_5411553093200887715_n.jpg?oh=076068798530280e01a3ea27e364f937&oe=567AD73A"
},
 {
  "name":"RockBar",
  "id":"391180544231322",
  "lat":"48.8793602",
  "lng":"2.34586",
  "address":"42 rue de  Rochechouart  75009 Paris",
  "pins": ["bieres","rock","terrasse"],
  "picture":"https://fbcdn-profile-a.akamaihd.net/hprofile-ak-xap1/v/t1.0-1/p50x50/1146513_703528719663168_1024438448_n.jpg?oh=cc3e72dc0731362e4995d29a5c4c1fcd&oe=5663BA9B&__gda__=1451069989_b38a3012d7b691e0ef2d80fac7a32bbf"
},
 {
  "name":"Roi de Pique",
  "id":"187956684696979",
  "lat":"48.863350609",
  "lng":"2.35842458297",
  "address":"126 rue du temple 75003 Paris",
  "pins": ["rock","timeout","terrasse"],
  "picture":"https://fbcdn-profile-a.akamaihd.net/hprofile-ak-prn2/v/t1.0-1/c0.0.50.50/p50x50/10858383_380537472105565_6209543787915233073_n.jpg?oh=bdfb0660841b99376df4e6618af4f208&oe=567627BC&__gda__=1449938745_06773e319b5c7d7d0a060518384d95de"
},
 {
  "name":"Rosa Bonheur",
  "id":"158025674508",
  "lat":"48.8800512168",
  "lng":"2.38636647796",
  "address":"2, allée de la Cascade 75019 Paris",
  "pins": ["rock","lebonbon","terrasse"],
  "picture":"https://fbcdn-profile-a.akamaihd.net/hprofile-ak-xfa1/v/t1.0-1/c17.0.50.50/p50x50/1395327_10151950098979509_303708180_n.jpg?oh=f990215ba215ef3913d562c3e655afaf&oe=566EC699&__gda__=1449154261_db33cc31d8b675c33ed72a5b5be58837"
},
 {
  "name":"Rosebud",
  "id":"393245130724651",
  "lat":"48.8503450143",
  "lng":"2.33910627635",
  "address":"4 Place de l'Odéon 75006 Paris",
  "pins": ["timeout","lebonbon","rock"],
  "picture":"https://scontent.xx.fbcdn.net/hprofile-xtp1/v/t1.0-1/c8.0.50.50/p50x50/10177343_643853942330434_1474325070791351220_n.jpg?oh=656007d6e0bd40ff4c557dc196f2daeb&oe=566C25BC"
},
 {
  "name":"Rosemary",
  "id":"789970911049940",
  "lat":"48.8487330598",
  "lng":"2.36537826098",
  "address":"4 rue Crillon 75004 Paris",
  "pins": ["rock","terrasse","timeout"],
  "picture":"https://scontent.xx.fbcdn.net/hprofile-xpa1/v/t1.0-1/p50x50/11080946_807497499297281_8768427800216341062_n.jpg?oh=f0e2004dd54ecbfa801ffc3a18acf53f&oe=5673B872"
},
 {
  "name":"Sancerre",
  "id":"156357591049618",
  "lat":"48.8849983",
  "lng":"2.3369401",
  "address":"35 Rue des Abbesses 75018 Paris",
  "pins": ["rock","timeout"],
  "picture":"https://scontent.xx.fbcdn.net/hprofile-xft1/v/t1.0-1/p50x50/1620779_213128448881319_2050800953_n.jpg?oh=fa67aee9e0196735e34e66f0f0b99d8f&oe=566B0CC0"
},
 {
  "name":"SANZ By Bizz’art",
  "id":"373109796033427",
  "lat":"48.8522491",
  "lng":"2.3728399",
  "address":"49 rue du Faubourg Saint Antoine 75011 Paris",
  "pins": ["terrasse","rock"],
  "picture":"https://fbcdn-profile-a.akamaihd.net/hprofile-ak-xat1/v/t1.0-1/p50x50/10934089_928866463791088_944282824073901999_n.jpg?oh=43f48b8005c4214f6a7de060d46c07d8&oe=567637A7&__gda__=1454049484_ce952904a5cbfdf354f4df8e14b567a8"
},
 {
  "name":"Sir Winston",
  "id":"586199224728159",
  "lat":"48.8722305",
  "lng":"2.29478",
  "address":"5, rue Presbourg 75016 Paris",
  "pins": ["terrasse","rock"],
  "picture":"https://fbcdn-profile-a.akamaihd.net/hprofile-ak-xfa1/v/t1.0-1/c0.0.50.50/p50x50/1932372_807988229215923_1625177630_n.jpg?oh=67cc61f44ceb816e785b8084005dc0ff&oe=56719530&__gda__=1449669558_daebccf0600079fc095a7d3ee5b8d767"
},
 {
  "name":"So What",
  "id":"171693449288",
  "lat":"48.8562698",
  "lng":"2.3582799",
  "address":"30 rue du roi de sicile 75004 Paris",
  "pins": ["rock","timeout"],
  "picture":"https://fbcdn-profile-a.akamaihd.net/hprofile-ak-xaf1/v/t1.0-1/p50x50/293867_10151319642129289_1492669734_n.jpg?oh=c8605e33c4c9402e7f7b10a5d04f1e80&oe=567B29AF&__gda__=1453906338_646e16305bb145b9c5aa45468f909e7e"
},
 {
  "name":"Sof's bar",
  "id":"118281381601052",
  "lat":"48.86768",
  "lng":"2.34116",
  "address":"81 Rue Réaumur  75002 Paris",
  "pins": ["lebonbon","rock"],
  "picture":"https://scontent.xx.fbcdn.net/hprofile-xfp1/v/t1.0-1/c7.0.50.50/p50x50/10517540_647669971995521_4744067702391464126_n.jpg?oh=3b922e98b07f2761ebab74e398cfaa07&oe=567A59A0"
},
 {
  "name":"Swan Bar",
  "id":"119774581529336",
  "lat":"48.8403091",
  "lng":"2.33533",
  "address":"165 bd du Montparnase 75006 Paris",
  "pins": ["rock","timeout"],
  "picture":"https://fbcdn-profile-a.akamaihd.net/hprofile-ak-prn2/v/t1.0-1/c65.28.255.255/s50x50/537164_119775861529208_393836799_n.png?oh=281c5dc6ea2f1b357afa3b93ffa82e4b&oe=565E27FB&__gda__=1450867720_9944575aa726d60b1c8213a0d14aae5a"
},
 {
  "name":"Tambour",
  "id":"451156238289222",
  "lat":"48.854599",
  "lng":"2.35008",
  "address":"5 rue d'Arcole 75004 Paris",
  "pins": ["timeout","rock"],
  "picture":"https://fbcdn-profile-a.akamaihd.net/hprofile-ak-ash2/v/t1.0-1/c39.39.490.490/s50x50/533638_451438858260960_1155101161_n.jpg?oh=a15b8d94b1efde4f4372d6d993cf17d0&oe=5671C807&__gda__=1449395285_73578c080c40eafb985d1046dc75848e"
},
 {
  "name":"The Bottle Shop",
  "id":"219349558188826",
  "lat":"48.8511696",
  "lng":"2.3785501",
  "address":"5, rue Trousseau 75011 Paris",
  "pins": ["rock","lebonbon"],
  "picture":"https://fbcdn-profile-a.akamaihd.net/hprofile-ak-xfp1/v/t1.0-1/c12.12.155.155/s50x50/1743501_228632173927231_1456018581_n.jpg?oh=39473c275abf787484b5e6e4ec498ffe&oe=5670A7C7&__gda__=1449379813_b4fed496af35274f8e077f153149e28a"
},
 {
  "name":"The Brooklyn",
  "id":"432424223499026",
  "lat":"48.8613701",
  "lng":"2.3507099",
  "address":"58 rue Quincampoix 75004 Paris",
  "pins": ["lebonbon","rock"],
  "picture":"https://fbcdn-profile-a.akamaihd.net/static-ak/rsrc.php/v2/yW/r/U2hFrus9i5v.png"
},
 {
  "name":"The Cork and Cavan",
  "id":"159732814047116",
  "lat":"48.8713417",
  "lng":"2.3657899",
  "address":"70 Quai de Jemmapes 75010 Paris",
  "pins": ["rock","lebonbon"],
  "picture":"https://fbcdn-profile-a.akamaihd.net/static-ak/rsrc.php/v2/yW/r/U2hFrus9i5v.png"
},
 {
  "name":"The Green Goose",
  "id":"224515764422038",
  "lat":"48.8503637107",
  "lng":"2.39062771432",
  "address":"19 rue des Boulets, 75011 75011 Paris",
  "pins": ["timeout","rock"],
  "picture":"https://fbcdn-profile-a.akamaihd.net/static-ak/rsrc.php/v2/yW/r/U2hFrus9i5v.png"
},
 {
  "name":"The Lab",
  "id":"166827026750013",
  "lat":"48.8548652032",
  "lng":"2.37176141782",
  "address":"07 rue Saint-Sabin 75011 Paris",
  "pins": ["rock","timeout"],
  "picture":"https://fbcdn-profile-a.akamaihd.net/hprofile-ak-xfa1/v/t1.0-1/c0.0.50.50/p50x50/386634_166864496746266_2134896285_n.jpg?oh=ddafea60fb8574f9eb8b79b1ea60f436&oe=56698E1E&__gda__=1449578830_eff0436204cf867c3f1200101b95f621"
},
 {
  "name":"Tigre",
  "id":"154798764536863",
  "lat":"48.8648266822",
  "lng":"2.33554554705",
  "address":"5 Rue Molière, Palais Royal 75001 Paris",
  "pins": ["timeout","rock"],
  "picture":"https://scontent.xx.fbcdn.net/hprofile-xpf1/v/t1.0-1/c14.14.172.172/s50x50/529497_600189946664407_2144752869_n.jpg?oh=c113dd37b25c5184fc4c531a3bafc94f&oe=5671BB99"
},
 {
  "name":"Tiki Lounge",
  "id":"185701458195176",
  "lat":"48.8682518",
  "lng":"2.37113",
  "address":"26 bis, rue de la Fontaine au Roi 75011 Paris",
  "pins": ["rock","timeout"],
  "picture":"https://scontent.xx.fbcdn.net/hprofile-xpa1/v/t1.0-1/p50x50/1464101_507394529359199_430934502_n.jpg?oh=97462b41c14b571a1798af1965729073&oe=566429B6"
},
 {
  "name":"Tireuse",
  "id":"264433247016169",
  "lat":"48.8474388",
  "lng":"2.3471401",
  "address":"18 rue Laplace 75005 Paris",
  "pins": ["rock","terrasse"],
  "picture":"https://fbcdn-profile-a.akamaihd.net/hprofile-ak-xap1/v/t1.0-1/p50x50/10438339_517216518404506_7304333549471247341_n.png?oh=dcd74740ece2c326137c4b145307c68e&oe=5665E11F&__gda__=1450364457_75d23494468f8bbad56212ca6f4a5358"
},
 {
  "name":"Titan Club",
  "id":"127993307251313",
  "lat":"48.8839417",
  "lng":"2.3271699",
  "address":"1 Av Clichy 75017 Paris",
  "pins": ["bieres","rock"],
  "picture":"https://fbcdn-profile-a.akamaihd.net/hprofile-ak-frc3/v/t1.0-1/p50x50/1480624_10151805493922434_1511797203_n.jpg?oh=f47ee2f1071a150497b1604f6893f4d8&oe=566DF7EA&__gda__=1451020561_92822a39a2b971ec42d31588fabae99e"
},
 {
  "name":"Tunnel Paris",
  "id":"716625605037399",
  "lat":"48.8174380969",
  "lng":"2.25183631272",
  "address":"5 Chemin des Montquartiers 92130 Issy-les-Moulineaux",
  "pins": ["timeout","rock"],
  "picture":"https://scontent.xx.fbcdn.net/hprofile-xap1/v/t1.0-1/p50x50/1604894_716677935032166_1868601592_n.jpg?oh=c62c0129c7e7db25b20922bdb697f691&oe=566FDF19"
},
 {
  "name":"Twenty One Sound Bar",
  "id":"1025894934088377",
  "lat":"48.8516808",
  "lng":"2.3807001",
  "address":"20 rue de la forge royale  75011 Paris",
  "pins": ["rock","lebonbon"],
  "picture":"https://scontent.xx.fbcdn.net/hprofile-xaf1/v/t1.0-1/p50x50/10469776_1025895100755027_6797275642855670720_n.jpg?oh=894a4771bc6e212f9eaa723e484f670a&oe=56739DAF"
},
 {
  "name":"Uma",
  "id":"667710979990795",
  "lat":"48.8651314",
  "lng":"2.3304999",
  "address":"7 rue du 29 juillet 75001 Paris",
  "pins": ["lebonbon","rock","bieres","terrasse"],
  "picture":"https://fbcdn-profile-a.akamaihd.net/hprofile-ak-xtf1/v/t1.0-1/p50x50/11128173_783018325126726_5271713097777143439_n.png?oh=c2f90f652392b41796c6992b8fa4d9c2&oe=566B8B1B&__gda__=1450295389_555d996e0ae64e336d489a01898cb35c"
},
 {
  "name":"Venus noire",
  "id":"76197249829",
  "lat":"48.8535995",
  "lng":"2.34285",
  "address":"25, rue de l'hirondelle 75006 Paris",
  "pins": ["rock","timeout"],
  "picture":"https://fbcdn-profile-a.akamaihd.net/hprofile-ak-xaf1/v/t1.0-1/c22.22.278.278/s50x50/541342_10151175587799830_757476605_n.jpg?oh=ef683a0c35db4d53c3b290b7e8766217&oe=56A9382B&__gda__=1450981816_dc18f050126a8f4474a1d4da8c7643ec"
},
 {
  "name":"Verre Volé",
  "id":"135322473181902",
  "lat":"48.8642693",
  "lng":"2.3717",
  "address":"l'épicerie du verre volé au 54 bis rue de la Folie Méricourt 75011 Paris",
  "pins": ["terrasse","rock"],
  "picture":"https://fbcdn-profile-a.akamaihd.net/hprofile-ak-prn2/v/t1.0-1/c20.20.252.252/s50x50/1231701_554985454548933_2142752909_n.jpg?oh=0c1c8afad562a002ffab8b20403b10f4&oe=5661E7A4&__gda__=1450031281_96721a915b3ceffc6750c77bf17e68fc"
},
 {
  "name":"Vivant",
  "id":"207827682569373",
  "lat":"48.8739049859",
  "lng":"2.34991365746",
  "address":"43 rue des petites écuries 75010 Paris",
  "pins": ["terrasse","rock"],
  "picture":"https://fbcdn-profile-a.akamaihd.net/hprofile-ak-xpa1/v/t1.0-1/c66.66.828.828/s50x50/1170952_651631294855674_1012281543_n.jpg?oh=b50f3601142605340dd000dd19dbe662&oe=5677D4F4&__gda__=1451089441_4fa9c103dba7fae81ec4e90d37ba11ee"
},
 {
  "name":"Voltigeur",
  "id":"154523461250687",
  "lat":"48.8582497",
  "lng":"2.35941",
  "address":"45, rue des francs-bourgeois 75004 Paris",
  "pins": ["rock","timeout"],
  "picture":"https://scontent.xx.fbcdn.net/hprofile-xpa1/v/l/t1.0-1/p50x50/1467274_187622048109009_1666660469_n.jpg?oh=d2aa038d75de2790554d8f14c6e319e9&oe=566FA800"
},
 {
  "name":"W.O.S. Bar",
  "id":"155519271145813",
  "lat":"48.8462296",
  "lng":"2.3429599",
  "address":"184 rue Saint Jacques 75005 Paris",
  "pins": ["lebonbon","rock"],
  "picture":"https://fbcdn-profile-a.akamaihd.net/static-ak/rsrc.php/v2/yW/r/U2hFrus9i5v.png"
},
 {
  "name":"Zak Bar",
  "id":"78416574558",
  "lat":"48.8672791",
  "lng":"2.3852999",
  "address":"3 rue victor letalle 75020 Paris",
  "pins": ["rock","timeout"],
  "picture":"https://scontent.xx.fbcdn.net/hprofile-xpa1/v/t1.0-1/c64.64.799.799/s50x50/1148970_10151796933789559_2077876823_n.jpg?oh=052402256f67b51bd165d8a15351128e&oe=56761264"
},
 {
  "name":"Zen Zoo",
  "id":"259684960715844",
  "lat":"48.8677483",
  "lng":"2.3369601",
  "address":"13 Rue Chabanais 75002 Paris",
  "pins": ["timeout","rock"],
  "picture":"https://fbcdn-profile-a.akamaihd.net/hprofile-ak-xfa1/v/t1.0-1/c41.11.138.138/s50x50/226142_259685924049081_8069704_n.jpg?oh=bbb83ef85475276781cc7a4f844555e2&oe=567374C1&__gda__=1454011207_76b14499962d70b41a145972cc6cb146"
}]
}
